{
  "chapter": 98,
  "total_lines": 163,
  "characters_in_chapter": [
    "char_narrator",
    "char_417",
    "char_516",
    "char_515",
    "char_000",
    "char_457"
  ],
  "character_line_counts": {
    "char_narrator": 109,
    "char_417": 29,
    "char_516": 12,
    "char_515": 1,
    "char_000": 11,
    "char_457": 1
  },
  "emotion_distribution": {
    "neutral": 150,
    "anger": 3,
    "curious": 2,
    "surprise": 2,
    "pain": 1,
    "confusion": 2,
    "fear": 2,
    "joy": 1
  },
  "lines": [
    {
      "line_id": "line_000001",
      "character_id": "char_narrator",
      "character_name": "Narrator",
      "text": "Faced with his sister ’s question , all Klein could do was reply with a regretful smile , “ Sore muscles . ”",
      "emotion": "neutral",
      "start_token": 229982,
      "end_token": 230004,
      "sentence_id": 15322,
      "paragraph_id": 0,
      "chapter": 98
    },
    {
      "line_id": "line_000002",
      "character_id": "char_417",
      "character_name": "Klein",
      "text": "He originally believed that by consuming the Sequence potion , his constitution would be enhanced as a Beyonder , but the harsh reality told him that a Seer ’s stats points were all allocated to his spirituality , mind , intuition , and interpretation .",
      "emotion": "neutral",
      "start_token": 230005,
      "end_token": 230049,
      "sentence_id": 15323,
      "paragraph_id": 0,
      "chapter": 98
    },
    {
      "line_id": "line_000003",
      "character_id": "char_narrator",
      "character_name": "Narrator",
      "text": "It did n’t aid him in adjusting to combat training quickly .",
      "emotion": "neutral",
      "start_token": 230050,
      "end_token": 230061,
      "sentence_id": 15324,
      "paragraph_id": 0,
      "chapter": 98
    },
    {
      "line_id": "line_000004",
      "character_id": "char_417",
      "character_name": "Klein",
      "text": "As for the original Klein , he had focused on his studies early on and had suffered from malnutrition .",
      "emotion": "neutral",
      "start_token": 230062,
      "end_token": 230081,
      "sentence_id": 15325,
      "paragraph_id": 0,
      "chapter": 98
    },
    {
      "line_id": "line_000005",
      "character_id": "char_narrator",
      "character_name": "Narrator",
      "text": "That led him to possess a below - average physical condition .",
      "emotion": "anger",
      "start_token": 230082,
      "end_token": 230093,
      "sentence_id": 15326,
      "paragraph_id": 0,
      "chapter": 98
    },
    {
      "line_id": "line_000006",
      "character_id": "char_narrator",
      "character_name": "Narrator",
      "text": "The fact that he was having ‘ after effects ’ from working out was to be expected .",
      "emotion": "neutral",
      "start_token": 230094,
      "end_token": 230111,
      "sentence_id": 15327,
      "paragraph_id": 0,
      "chapter": 98
    },
    {
      "line_id": "line_000007",
      "character_id": "char_narrator",
      "character_name": "Narrator",
      "text": "“ Sore muscles ?",
      "emotion": "neutral",
      "start_token": 230112,
      "end_token": 230115,
      "sentence_id": 15328,
      "paragraph_id": 0,
      "chapter": 98
    },
    {
      "line_id": "line_000008",
      "character_id": "char_516",
      "character_name": "Melissa",
      "text": "I remember you returning after dinner last night and you did n’t do anything else ...",
      "emotion": "neutral",
      "start_token": 230116,
      "end_token": 230131,
      "sentence_id": 15329,
      "paragraph_id": 0,
      "chapter": 98
    },
    {
      "line_id": "line_000009",
      "character_id": "char_narrator",
      "character_name": "Narrator",
      "text": "Does alcohol cause sore muscles ? ”",
      "emotion": "neutral",
      "start_token": 230132,
      "end_token": 230138,
      "sentence_id": 15330,
      "paragraph_id": 0,
      "chapter": 98
    },
    {
      "line_id": "line_000010",
      "character_id": "char_516",
      "character_name": "Melissa",
      "text": "Melissa inquired with an inquisitive look .",
      "emotion": "curious",
      "start_token": 230139,
      "end_token": 230145,
      "sentence_id": 15331,
      "paragraph_id": 0,
      "chapter": 98
    },
    {
      "line_id": "line_000011",
      "character_id": "char_narrator",
      "character_name": "Narrator",
      "text": "Does alcohol cause sore muscles ...",
      "emotion": "neutral",
      "start_token": 230146,
      "end_token": 230151,
      "sentence_id": 15332,
      "paragraph_id": 0,
      "chapter": 98
    },
    {
      "line_id": "line_000012",
      "character_id": "char_515",
      "character_name": "Sis",
      "text": "Sis , that question ... ca n’t help but make me have inappropriate thoughts ... Klein laughed dryly and said , “ No , this has nothing to do with alcohol .",
      "emotion": "neutral",
      "start_token": 230152,
      "end_token": 230183,
      "sentence_id": 15333,
      "paragraph_id": 0,
      "chapter": 98
    },
    {
      "line_id": "line_000013",
      "character_id": "char_narrator",
      "character_name": "Narrator",
      "text": "It was from yesterday afternoon .",
      "emotion": "neutral",
      "start_token": 230184,
      "end_token": 230189,
      "sentence_id": 15334,
      "paragraph_id": 0,
      "chapter": 98
    },
    {
      "line_id": "line_000014",
      "character_id": "char_417",
      "character_name": "Klein",
      "text": "I joined the company ’s combat training . ”",
      "emotion": "neutral",
      "start_token": 230190,
      "end_token": 230198,
      "sentence_id": 15335,
      "paragraph_id": 0,
      "chapter": 98
    },
    {
      "line_id": "line_000015",
      "character_id": "char_narrator",
      "character_name": "Narrator",
      "text": "“ Combat ? ”",
      "emotion": "neutral",
      "start_token": 230199,
      "end_token": 230202,
      "sentence_id": 15336,
      "paragraph_id": 0,
      "chapter": 98
    },
    {
      "line_id": "line_000016",
      "character_id": "char_516",
      "character_name": "Melissa",
      "text": "Melissa was even more astonished .",
      "emotion": "surprise",
      "start_token": 230203,
      "end_token": 230208,
      "sentence_id": 15337,
      "paragraph_id": 0,
      "chapter": 98
    },
    {
      "line_id": "line_000017",
      "character_id": "char_417",
      "character_name": "Klein",
      "text": "Klein organized his thoughts and said , “ Well , this is what happened .",
      "emotion": "neutral",
      "start_token": 230209,
      "end_token": 230223,
      "sentence_id": 15338,
      "paragraph_id": 0,
      "chapter": 98
    },
    {
      "line_id": "line_000018",
      "character_id": "char_417",
      "character_name": "Klein",
      "text": "I considered it and believe that as a historical and relic consultant of a security company , it ’s impossible for me to stay in the office or port warehouse forever .",
      "emotion": "neutral",
      "start_token": 230224,
      "end_token": 230255,
      "sentence_id": 15339,
      "paragraph_id": 0,
      "chapter": 98
    },
    {
      "line_id": "line_000019",
      "character_id": "char_narrator",
      "character_name": "Narrator",
      "text": "Perhaps there will come a day when I have to accompany them to the villages or an ancient castle , to the site of some relic .",
      "emotion": "neutral",
      "start_token": 230256,
      "end_token": 230282,
      "sentence_id": 15340,
      "paragraph_id": 0,
      "chapter": 98
    },
    {
      "line_id": "line_000020",
      "character_id": "char_narrator",
      "character_name": "Narrator",
      "text": "That might require me to hike , to cross rivers , and to walk a lot .",
      "emotion": "neutral",
      "start_token": 230283,
      "end_token": 230299,
      "sentence_id": 15341,
      "paragraph_id": 0,
      "chapter": 98
    },
    {
      "line_id": "line_000021",
      "character_id": "char_417",
      "character_name": "Klein",
      "text": "I ’ll have to endure all sorts of tests posed by nature , so I have to possess a sufficiently healthy body . ”",
      "emotion": "neutral",
      "start_token": 230300,
      "end_token": 230323,
      "sentence_id": 15342,
      "paragraph_id": 0,
      "chapter": 98
    },
    {
      "line_id": "line_000022",
      "character_id": "char_narrator",
      "character_name": "Narrator",
      "text": "“ So you joined combat training to enhance your stamina ? ”",
      "emotion": "neutral",
      "start_token": 230324,
      "end_token": 230335,
      "sentence_id": 15343,
      "paragraph_id": 0,
      "chapter": 98
    },
    {
      "line_id": "line_000023",
      "character_id": "char_516",
      "character_name": "Melissa",
      "text": "Melissa seemed to understand her brother ’s intention .",
      "emotion": "neutral",
      "start_token": 230336,
      "end_token": 230344,
      "sentence_id": 15344,
      "paragraph_id": 0,
      "chapter": 98
    },
    {
      "line_id": "line_000024",
      "character_id": "char_417",
      "character_name": "Klein",
      "text": "“ That ’s right , ” Klein answered with great affirmation .",
      "emotion": "neutral",
      "start_token": 230345,
      "end_token": 230356,
      "sentence_id": 15345,
      "paragraph_id": 0,
      "chapter": 98
    },
    {
      "line_id": "line_000025",
      "character_id": "char_516",
      "character_name": "Melissa",
      "text": "Melissa said with a frown , “ But that is n’t gentlemanly ...",
      "emotion": "neutral",
      "start_token": 230357,
      "end_token": 230369,
      "sentence_id": 15346,
      "paragraph_id": 0,
      "chapter": 98
    },
    {
      "line_id": "line_000026",
      "character_id": "char_narrator",
      "character_name": "Narrator",
      "text": "Do n’t you always keep yourself to the standards of a professor ?",
      "emotion": "neutral",
      "start_token": 230370,
      "end_token": 230382,
      "sentence_id": 15347,
      "paragraph_id": 0,
      "chapter": 98
    },
    {
      "line_id": "line_000027",
      "character_id": "char_narrator",
      "character_name": "Narrator",
      "text": "A professor only requires the ability to read historical documents , ponder over difficult questions , and maintain a polite and gentlemanly demeanor .",
      "emotion": "neutral",
      "start_token": 230383,
      "end_token": 230406,
      "sentence_id": 15348,
      "paragraph_id": 0,
      "chapter": 98
    },
    {
      "line_id": "line_000028",
      "character_id": "char_narrator",
      "character_name": "Narrator",
      "text": "“ Of course , I ’m not saying that those are n’t all good things .",
      "emotion": "neutral",
      "start_token": 230407,
      "end_token": 230422,
      "sentence_id": 15349,
      "paragraph_id": 0,
      "chapter": 98
    },
    {
      "line_id": "line_000029",
      "character_id": "char_000",
      "character_name": "Character_10000",
      "text": "I prefer men who can solve problems on their own , regardless of whether that solution requires brawn or brain . ”",
      "emotion": "neutral",
      "start_token": 230423,
      "end_token": 230444,
      "sentence_id": 15350,
      "paragraph_id": 0,
      "chapter": 98
    },
    {
      "line_id": "line_000030",
      "character_id": "char_516",
      "character_name": "Melissa",
      "text": "Melissa smiled .",
      "emotion": "neutral",
      "start_token": 230445,
      "end_token": 230447,
      "sentence_id": 15351,
      "paragraph_id": 0,
      "chapter": 98
    },
    {
      "line_id": "line_000031",
      "character_id": "char_417",
      "character_name": "Klein",
      "text": "Klein smiled and said , “ No , no , no , Melissa .",
      "emotion": "neutral",
      "start_token": 230448,
      "end_token": 230461,
      "sentence_id": 15352,
      "paragraph_id": 0,
      "chapter": 98
    },
    {
      "line_id": "line_000032",
      "character_id": "char_516",
      "character_name": "Melissa",
      "text": "Your definition of a professor contains a misconception .",
      "emotion": "neutral",
      "start_token": 230462,
      "end_token": 230470,
      "sentence_id": 15353,
      "paragraph_id": 0,
      "chapter": 98
    },
    {
      "line_id": "line_000033",
      "character_id": "char_narrator",
      "character_name": "Narrator",
      "text": "A true professor can communicate with people gently and politely , but he can also educate the other person using the principles of physics by raising a cane to convince someone when there is an obstacle in communication . ”",
      "emotion": "neutral",
      "start_token": 230471,
      "end_token": 230510,
      "sentence_id": 15354,
      "paragraph_id": 0,
      "chapter": 98
    },
    {
      "line_id": "line_000034",
      "character_id": "char_narrator",
      "character_name": "Narrator",
      "text": "“ Principles of physics ... ”",
      "emotion": "neutral",
      "start_token": 230511,
      "end_token": 230516,
      "sentence_id": 15355,
      "paragraph_id": 0,
      "chapter": 98
    },
    {
      "line_id": "line_000035",
      "character_id": "char_516",
      "character_name": "Melissa",
      "text": "Melissa was momentarily at a loss , but she quickly understood what her brother was saying .",
      "emotion": "neutral",
      "start_token": 230517,
      "end_token": 230533,
      "sentence_id": 15356,
      "paragraph_id": 0,
      "chapter": 98
    },
    {
      "line_id": "line_000036",
      "character_id": "char_516",
      "character_name": "Melissa",
      "text": "She was suddenly unable to retort him .",
      "emotion": "neutral",
      "start_token": 230534,
      "end_token": 230541,
      "sentence_id": 15357,
      "paragraph_id": 0,
      "chapter": 98
    },
    {
      "line_id": "line_000037",
      "character_id": "char_417",
      "character_name": "Klein",
      "text": "Klein did n’t say anything more but widened his pace with great difficulty as he headed for the bathroom .",
      "emotion": "neutral",
      "start_token": 230542,
      "end_token": 230561,
      "sentence_id": 15358,
      "paragraph_id": 0,
      "chapter": 98
    },
    {
      "line_id": "line_000038",
      "character_id": "char_516",
      "character_name": "Melissa",
      "text": "Melissa stood there and looked for a few seconds .",
      "emotion": "neutral",
      "start_token": 230562,
      "end_token": 230571,
      "sentence_id": 15359,
      "paragraph_id": 0,
      "chapter": 98
    },
    {
      "line_id": "line_000039",
      "character_id": "char_516",
      "character_name": "Melissa",
      "text": "She suddenly shook her head and caught up to Klein .",
      "emotion": "neutral",
      "start_token": 230572,
      "end_token": 230582,
      "sentence_id": 15360,
      "paragraph_id": 0,
      "chapter": 98
    },
    {
      "line_id": "line_000040",
      "character_id": "char_516",
      "character_name": "Melissa",
      "text": "“ Do you need my help ? ” She posed as if she was supporting someone .",
      "emotion": "neutral",
      "start_token": 230583,
      "end_token": 230599,
      "sentence_id": 15361,
      "paragraph_id": 0,
      "chapter": 98
    },
    {
      "line_id": "line_000041",
      "character_id": "char_narrator",
      "character_name": "Narrator",
      "text": "“ No , there ’s no need to .",
      "emotion": "neutral",
      "start_token": 230600,
      "end_token": 230608,
      "sentence_id": 15362,
      "paragraph_id": 0,
      "chapter": 98
    },
    {
      "line_id": "line_000042",
      "character_id": "char_000",
      "character_name": "Character_10000",
      "text": "I was hamming it up a bit earlier . ”",
      "emotion": "neutral",
      "start_token": 230609,
      "end_token": 230618,
      "sentence_id": 15363,
      "paragraph_id": 0,
      "chapter": 98
    },
    {
      "line_id": "line_000043",
      "character_id": "char_417",
      "character_name": "Klein",
      "text": "Klein felt humiliated .",
      "emotion": "neutral",
      "start_token": 230619,
      "end_token": 230622,
      "sentence_id": 15364,
      "paragraph_id": 0,
      "chapter": 98
    },
    {
      "line_id": "line_000044",
      "character_id": "char_417",
      "character_name": "Klein",
      "text": "He suddenly stood straight and walked normally .",
      "emotion": "neutral",
      "start_token": 230623,
      "end_token": 230630,
      "sentence_id": 15365,
      "paragraph_id": 0,
      "chapter": 98
    },
    {
      "line_id": "line_000045",
      "character_id": "char_narrator",
      "character_name": "Narrator",
      "text": "Watching her brother walk steadily to the washroom and close the door , Melissa pursed her lips and muttered , “ Klein is getting more and more pretentious ...",
      "emotion": "neutral",
      "start_token": 230631,
      "end_token": 230659,
      "sentence_id": 15366,
      "paragraph_id": 0,
      "chapter": 98
    },
    {
      "line_id": "line_000046",
      "character_id": "char_000",
      "character_name": "Character_10000",
      "text": "I even believed that his muscle soreness was really that serious ... ”",
      "emotion": "neutral",
      "start_token": 230660,
      "end_token": 230672,
      "sentence_id": 15367,
      "paragraph_id": 0,
      "chapter": 98
    },
    {
      "line_id": "line_000047",
      "character_id": "char_narrator",
      "character_name": "Narrator",
      "text": "In the bathroom , Klein stood behind the tightly shut door , his face suddenly contorting in pain .",
      "emotion": "pain",
      "start_token": 230673,
      "end_token": 230691,
      "sentence_id": 15368,
      "paragraph_id": 0,
      "chapter": 98
    },
    {
      "line_id": "line_000048",
      "character_id": "char_narrator",
      "character_name": "Narrator",
      "text": "Ouch , ouch , ouch ...",
      "emotion": "neutral",
      "start_token": 230692,
      "end_token": 230697,
      "sentence_id": 15369,
      "paragraph_id": 0,
      "chapter": 98
    },
    {
      "line_id": "line_000049",
      "character_id": "char_417",
      "character_name": "Klein",
      "text": "He held his breath , tensed his body , and stood there for a good seven or eight seconds .",
      "emotion": "neutral",
      "start_token": 230698,
      "end_token": 230717,
      "sentence_id": 15370,
      "paragraph_id": 0,
      "chapter": 98
    },
    {
      "line_id": "line_000050",
      "character_id": "char_narrator",
      "character_name": "Narrator",
      "text": "When he finally went downstairs with great effort , had breakfast , and saw Benson and Melissa off , his soreness finally began to ease .",
      "emotion": "neutral",
      "start_token": 230718,
      "end_token": 230743,
      "sentence_id": 15371,
      "paragraph_id": 0,
      "chapter": 98
    },
    {
      "line_id": "line_000051",
      "character_id": "char_narrator",
      "character_name": "Narrator",
      "text": "After resting for a little while , Klein took his cane , donned his top hat , and left the house , strolling towards the public carriage stop .",
      "emotion": "neutral",
      "start_token": 230744,
      "end_token": 230772,
      "sentence_id": 15372,
      "paragraph_id": 0,
      "chapter": 98
    },
    {
      "line_id": "line_000052",
      "character_id": "char_narrator",
      "character_name": "Narrator",
      "text": "...",
      "emotion": "neutral",
      "start_token": 230773,
      "end_token": 230773,
      "sentence_id": 15373,
      "paragraph_id": 0,
      "chapter": 98
    },
    {
      "line_id": "line_000053",
      "character_id": "char_narrator",
      "character_name": "Narrator",
      "text": "During the summer , Khoy University had trees with shade - providing foliage , flourishing with birds and luxuriant flowers .",
      "emotion": "neutral",
      "start_token": 230774,
      "end_token": 230794,
      "sentence_id": 15374,
      "paragraph_id": 0,
      "chapter": 98
    },
    {
      "line_id": "line_000054",
      "character_id": "char_narrator",
      "character_name": "Narrator",
      "text": "It was peaceful and calm .",
      "emotion": "neutral",
      "start_token": 230795,
      "end_token": 230800,
      "sentence_id": 15375,
      "paragraph_id": 0,
      "chapter": 98
    },
    {
      "line_id": "line_000055",
      "character_id": "char_narrator",
      "character_name": "Narrator",
      "text": "Walking along the river , Klein took a turn towards the history department .",
      "emotion": "neutral",
      "start_token": 230801,
      "end_token": 230814,
      "sentence_id": 15376,
      "paragraph_id": 0,
      "chapter": 98
    },
    {
      "line_id": "line_000056",
      "character_id": "char_narrator",
      "character_name": "Narrator",
      "text": "Then , he found the three - story building which showed its age and located his mentor ’s , Cohen Quentin ’s , office .",
      "emotion": "neutral",
      "start_token": 230815,
      "end_token": 230839,
      "sentence_id": 15377,
      "paragraph_id": 0,
      "chapter": 98
    },
    {
      "line_id": "line_000057",
      "character_id": "char_417",
      "character_name": "Klein",
      "text": "He knocked and entered the room , but he was shocked to see that the man sitting at his mentor ’s seat was the academic , Azik .",
      "emotion": "surprise",
      "start_token": 230840,
      "end_token": 230867,
      "sentence_id": 15378,
      "paragraph_id": 0,
      "chapter": 98
    },
    {
      "line_id": "line_000058",
      "character_id": "char_narrator",
      "character_name": "Narrator",
      "text": "“ Good morning , Mr. Azik , Where ’s my mentor ?",
      "emotion": "neutral",
      "start_token": 230868,
      "end_token": 230879,
      "sentence_id": 15379,
      "paragraph_id": 0,
      "chapter": 98
    },
    {
      "line_id": "line_000059",
      "character_id": "char_narrator",
      "character_name": "Narrator",
      "text": "We made an appointment by letter to meet here at ten , ” Klein asked , puzzled .",
      "emotion": "anger",
      "start_token": 230880,
      "end_token": 230897,
      "sentence_id": 15380,
      "paragraph_id": 0,
      "chapter": 98
    },
    {
      "line_id": "line_000060",
      "character_id": "char_narrator",
      "character_name": "Narrator",
      "text": "Azik , who was Cohen Quentin ’s best friend and often debated with his mentor regarding academic topics , smiled and said , “ Cohen had a last minute meeting and went to Tingen University .",
      "emotion": "neutral",
      "start_token": 230898,
      "end_token": 230933,
      "sentence_id": 15381,
      "paragraph_id": 0,
      "chapter": 98
    },
    {
      "line_id": "line_000061",
      "character_id": "char_457",
      "character_name": "Mentor",
      "text": "He asked me to wait for you here . ”",
      "emotion": "neutral",
      "start_token": 230934,
      "end_token": 230943,
      "sentence_id": 15382,
      "paragraph_id": 0,
      "chapter": 98
    },
    {
      "line_id": "line_000062",
      "character_id": "char_narrator",
      "character_name": "Narrator",
      "text": "He had bronze skin , an average height and build , black hair , brown eyes , and gentle facial features .",
      "emotion": "anger",
      "start_token": 230944,
      "end_token": 230965,
      "sentence_id": 15383,
      "paragraph_id": 0,
      "chapter": 98
    },
    {
      "line_id": "line_000063",
      "character_id": "char_narrator",
      "character_name": "Narrator",
      "text": "Being in his presence brought on an indescribable feeling , as though you could see in the man ’s eyes that he had been through the vicissitudes of life .",
      "emotion": "neutral",
      "start_token": 230966,
      "end_token": 230995,
      "sentence_id": 15384,
      "paragraph_id": 0,
      "chapter": 98
    },
    {
      "line_id": "line_000064",
      "character_id": "char_narrator",
      "character_name": "Narrator",
      "text": "Under his right ear was a tiny mole that one would n’t notice unless closely examined .",
      "emotion": "neutral",
      "start_token": 230996,
      "end_token": 231012,
      "sentence_id": 15385,
      "paragraph_id": 0,
      "chapter": 98
    },
    {
      "line_id": "line_000065",
      "character_id": "char_narrator",
      "character_name": "Narrator",
      "text": "Having said the reason , Azik suddenly frowned as he carefully observed Klein .",
      "emotion": "neutral",
      "start_token": 231013,
      "end_token": 231026,
      "sentence_id": 15386,
      "paragraph_id": 0,
      "chapter": 98
    },
    {
      "line_id": "line_000066",
      "character_id": "char_narrator",
      "character_name": "Narrator",
      "text": "Feeling confused by the sudden scrutiny , Klein looked at his attire .",
      "emotion": "confusion",
      "start_token": 231027,
      "end_token": 231039,
      "sentence_id": 15387,
      "paragraph_id": 0,
      "chapter": 98
    },
    {
      "line_id": "line_000067",
      "character_id": "char_narrator",
      "character_name": "Narrator",
      "text": "“ Have I committed some breach of etiquette ? ” Tuxedo , black vest , white shirt , black bow tie , dark colored trousers , leather boots with no buttons ... Everything seems normal ...",
      "emotion": "neutral",
      "start_token": 231040,
      "end_token": 231075,
      "sentence_id": 15388,
      "paragraph_id": 0,
      "chapter": 98
    },
    {
      "line_id": "line_000068",
      "character_id": "char_narrator",
      "character_name": "Narrator",
      "text": "Azik ’s brows eased and he chuckled softly .",
      "emotion": "neutral",
      "start_token": 231076,
      "end_token": 231084,
      "sentence_id": 15389,
      "paragraph_id": 0,
      "chapter": 98
    },
    {
      "line_id": "line_000069",
      "character_id": "char_narrator",
      "character_name": "Narrator",
      "text": "“ Do n’t mind me .",
      "emotion": "neutral",
      "start_token": 231085,
      "end_token": 231090,
      "sentence_id": 15390,
      "paragraph_id": 0,
      "chapter": 98
    },
    {
      "line_id": "line_000070",
      "character_id": "char_000",
      "character_name": "Character_10000",
      "text": "I suddenly noticed that you are way more energetic than before .",
      "emotion": "neutral",
      "start_token": 231091,
      "end_token": 231102,
      "sentence_id": 15391,
      "paragraph_id": 0,
      "chapter": 98
    },
    {
      "line_id": "line_000071",
      "character_id": "char_000",
      "character_name": "Character_10000",
      "text": "You look even more like a gentleman now . ”",
      "emotion": "neutral",
      "start_token": 231103,
      "end_token": 231112,
      "sentence_id": 15392,
      "paragraph_id": 0,
      "chapter": 98
    },
    {
      "line_id": "line_000072",
      "character_id": "char_000",
      "character_name": "Character_10000",
      "text": "“ Thank you for your compliment . ”",
      "emotion": "neutral",
      "start_token": 231113,
      "end_token": 231120,
      "sentence_id": 15393,
      "paragraph_id": 0,
      "chapter": 98
    },
    {
      "line_id": "line_000073",
      "character_id": "char_417",
      "character_name": "Klein",
      "text": "Klein accepted it calmly and asked , “ Mr. Azik , did my mentor manage to find the book ‘ Research of the Hornacis Main Peak ’s Relics ’ in the school library ? ” “ He found it with my assistance , ” Azik said , smiling gently .",
      "emotion": "neutral",
      "start_token": 231121,
      "end_token": 231170,
      "sentence_id": 15394,
      "paragraph_id": 0,
      "chapter": 98
    },
    {
      "line_id": "line_000074",
      "character_id": "char_narrator",
      "character_name": "Narrator",
      "text": "He then pulled open the drawer and took out a gray - covered book .",
      "emotion": "neutral",
      "start_token": 231171,
      "end_token": 231185,
      "sentence_id": 15395,
      "paragraph_id": 0,
      "chapter": 98
    },
    {
      "line_id": "line_000075",
      "character_id": "char_narrator",
      "character_name": "Narrator",
      "text": "“ You are no longer a Khoy University student anymore .",
      "emotion": "neutral",
      "start_token": 231186,
      "end_token": 231196,
      "sentence_id": 15396,
      "paragraph_id": 0,
      "chapter": 98
    },
    {
      "line_id": "line_000076",
      "character_id": "char_000",
      "character_name": "Character_10000",
      "text": "You can read it here , but you can not take it home . ”",
      "emotion": "neutral",
      "start_token": 231197,
      "end_token": 231211,
      "sentence_id": 15397,
      "paragraph_id": 0,
      "chapter": 98
    },
    {
      "line_id": "line_000077",
      "character_id": "char_narrator",
      "character_name": "Narrator",
      "text": "“ Alright . ”",
      "emotion": "neutral",
      "start_token": 231212,
      "end_token": 231215,
      "sentence_id": 15398,
      "paragraph_id": 0,
      "chapter": 98
    },
    {
      "line_id": "line_000078",
      "character_id": "char_417",
      "character_name": "Klein",
      "text": "Klein delightfully took the academic monograph , and with a hint of fear .",
      "emotion": "fear",
      "start_token": 231216,
      "end_token": 231229,
      "sentence_id": 15399,
      "paragraph_id": 0,
      "chapter": 98
    },
    {
      "line_id": "line_000079",
      "character_id": "char_narrator",
      "character_name": "Narrator",
      "text": "The book ’s design was fully in - line with the current trends ; it used hard paper as a hardcover and it was printed with an image like an abstract version of the main peak of Hornacis mountain range .",
      "emotion": "neutral",
      "start_token": 231230,
      "end_token": 231270,
      "sentence_id": 15400,
      "paragraph_id": 0,
      "chapter": 98
    },
    {
      "line_id": "line_000080",
      "character_id": "char_417",
      "character_name": "Klein",
      "text": "Klein took a glance and found a seat .",
      "emotion": "neutral",
      "start_token": 231271,
      "end_token": 231279,
      "sentence_id": 15401,
      "paragraph_id": 0,
      "chapter": 98
    },
    {
      "line_id": "line_000081",
      "character_id": "char_417",
      "character_name": "Klein",
      "text": "He flipped open the book and started reading carefully , line by line .",
      "emotion": "neutral",
      "start_token": 231280,
      "end_token": 231293,
      "sentence_id": 15402,
      "paragraph_id": 0,
      "chapter": 98
    },
    {
      "line_id": "line_000082",
      "character_id": "char_narrator",
      "character_name": "Narrator",
      "text": "As he became engrossed in the book , he suddenly realized that there was a cup of rich and fragrant coffee by his side .",
      "emotion": "neutral",
      "start_token": 231294,
      "end_token": 231318,
      "sentence_id": 15403,
      "paragraph_id": 0,
      "chapter": 98
    },
    {
      "line_id": "line_000083",
      "character_id": "char_narrator",
      "character_name": "Narrator",
      "text": "“ Help yourself to the sugar and milk . ”",
      "emotion": "neutral",
      "start_token": 231319,
      "end_token": 231328,
      "sentence_id": 15404,
      "paragraph_id": 0,
      "chapter": 98
    },
    {
      "line_id": "line_000084",
      "character_id": "char_narrator",
      "character_name": "Narrator",
      "text": "Azik put down the silver saucer and pointed at the milk jar and sugar container .",
      "emotion": "neutral",
      "start_token": 231329,
      "end_token": 231344,
      "sentence_id": 15405,
      "paragraph_id": 0,
      "chapter": 98
    },
    {
      "line_id": "line_000085",
      "character_id": "char_000",
      "character_name": "Character_10000",
      "text": "“ Thank you . ”",
      "emotion": "neutral",
      "start_token": 231345,
      "end_token": 231349,
      "sentence_id": 15406,
      "paragraph_id": 0,
      "chapter": 98
    },
    {
      "line_id": "line_000086",
      "character_id": "char_417",
      "character_name": "Klein",
      "text": "Klein nodded with gratitude .",
      "emotion": "neutral",
      "start_token": 231350,
      "end_token": 231354,
      "sentence_id": 15407,
      "paragraph_id": 0,
      "chapter": 98
    },
    {
      "line_id": "line_000087",
      "character_id": "char_417",
      "character_name": "Klein",
      "text": "He added three cubes of sugar and a teaspoon of milk before continuing to read his book .",
      "emotion": "neutral",
      "start_token": 231355,
      "end_token": 231372,
      "sentence_id": 15408,
      "paragraph_id": 0,
      "chapter": 98
    },
    {
      "line_id": "line_000088",
      "character_id": "char_narrator",
      "character_name": "Narrator",
      "text": "The book , Research of the Hornacis Main Peak ’s Relics , was not a very thick book .",
      "emotion": "neutral",
      "start_token": 231373,
      "end_token": 231391,
      "sentence_id": 15409,
      "paragraph_id": 0,
      "chapter": 98
    },
    {
      "line_id": "line_000089",
      "character_id": "char_417",
      "character_name": "Klein",
      "text": "Klein finished reading it when it was almost noon .",
      "emotion": "neutral",
      "start_token": 231392,
      "end_token": 231401,
      "sentence_id": 15410,
      "paragraph_id": 0,
      "chapter": 98
    },
    {
      "line_id": "line_000090",
      "character_id": "char_417",
      "character_name": "Klein",
      "text": "He took note of a few noteworthy points .",
      "emotion": "neutral",
      "start_token": 231402,
      "end_token": 231410,
      "sentence_id": 15411,
      "paragraph_id": 0,
      "chapter": 98
    },
    {
      "line_id": "line_000091",
      "character_id": "char_narrator",
      "character_name": "Narrator",
      "text": "First , the settlement on the main peak of Hornacis Mountain and its surrounding area was obviously an advanced civilization , which existed as part of an ancient nation .",
      "emotion": "neutral",
      "start_token": 231411,
      "end_token": 231440,
      "sentence_id": 15412,
      "paragraph_id": 0,
      "chapter": 98
    },
    {
      "line_id": "line_000092",
      "character_id": "char_narrator",
      "character_name": "Narrator",
      "text": "Second , from their wall murals , their perspective on life appears similar to that of humans .",
      "emotion": "neutral",
      "start_token": 231441,
      "end_token": 231458,
      "sentence_id": 15413,
      "paragraph_id": 0,
      "chapter": 98
    },
    {
      "line_id": "line_000093",
      "character_id": "char_000",
      "character_name": "Character_10000",
      "text": "I can assume for now that they were human .",
      "emotion": "neutral",
      "start_token": 231459,
      "end_token": 231468,
      "sentence_id": 15414,
      "paragraph_id": 0,
      "chapter": 98
    },
    {
      "line_id": "line_000094",
      "character_id": "char_narrator",
      "character_name": "Narrator",
      "text": "Third , they revered yet feared the darkness of the night .",
      "emotion": "fear",
      "start_token": 231469,
      "end_token": 231480,
      "sentence_id": 15415,
      "paragraph_id": 0,
      "chapter": 98
    },
    {
      "line_id": "line_000095",
      "character_id": "char_narrator",
      "character_name": "Narrator",
      "text": "Hence , they called their god the Ruler of the Evernight , Mother of the Sky .",
      "emotion": "neutral",
      "start_token": 231481,
      "end_token": 231497,
      "sentence_id": 15416,
      "paragraph_id": 0,
      "chapter": 98
    },
    {
      "line_id": "line_000096",
      "character_id": "char_narrator",
      "character_name": "Narrator",
      "text": "Fourth , the weirdest part is that researchers have n’t found any graves in the entire area , which initially seems to indicate that the people did n’t need to be buried , because they did n’t die .",
      "emotion": "neutral",
      "start_token": 231498,
      "end_token": 231536,
      "sentence_id": 15417,
      "paragraph_id": 0,
      "chapter": 98
    },
    {
      "line_id": "line_000097",
      "character_id": "char_narrator",
      "character_name": "Narrator",
      "text": "However , that would be contradictory to the contents of the wall murals .",
      "emotion": "neutral",
      "start_token": 231537,
      "end_token": 231550,
      "sentence_id": 15418,
      "paragraph_id": 0,
      "chapter": 98
    },
    {
      "line_id": "line_000098",
      "character_id": "char_narrator",
      "character_name": "Narrator",
      "text": "In the wall murals , the people in the nation believed that death is not the end .",
      "emotion": "neutral",
      "start_token": 231551,
      "end_token": 231568,
      "sentence_id": 15419,
      "paragraph_id": 0,
      "chapter": 98
    },
    {
      "line_id": "line_000099",
      "character_id": "char_narrator",
      "character_name": "Narrator",
      "text": "They believed that their deceased family would protect them in the night .",
      "emotion": "neutral",
      "start_token": 231569,
      "end_token": 231581,
      "sentence_id": 15420,
      "paragraph_id": 0,
      "chapter": 98
    },
    {
      "line_id": "line_000100",
      "character_id": "char_narrator",
      "character_name": "Narrator",
      "text": "Hence , they would keep their deceased family members at home , on the bed , by their side , for a full three days .",
      "emotion": "neutral",
      "start_token": 231582,
      "end_token": 231607,
      "sentence_id": 15421,
      "paragraph_id": 0,
      "chapter": 98
    },
    {
      "line_id": "line_000101",
      "character_id": "char_narrator",
      "character_name": "Narrator",
      "text": "There is nothing beyond that for the wall murals as it does n’t involve burials .",
      "emotion": "neutral",
      "start_token": 231608,
      "end_token": 231623,
      "sentence_id": 15422,
      "paragraph_id": 0,
      "chapter": 98
    },
    {
      "line_id": "line_000102",
      "character_id": "char_417",
      "character_name": "Klein",
      "text": "Klein took another sip of coffee and continued to write down his ‘ afterthoughts ’ in his notebook .",
      "emotion": "neutral",
      "start_token": 231624,
      "end_token": 231642,
      "sentence_id": 15423,
      "paragraph_id": 0,
      "chapter": 98
    },
    {
      "line_id": "line_000103",
      "character_id": "char_narrator",
      "character_name": "Narrator",
      "text": "Mother of the Sky , Skymother is such a grand title , while the Ruler of the Evernight obviously overlaps with the Evernight Goddess ...",
      "emotion": "neutral",
      "start_token": 231643,
      "end_token": 231667,
      "sentence_id": 15424,
      "paragraph_id": 0,
      "chapter": 98
    },
    {
      "line_id": "line_000104",
      "character_id": "char_narrator",
      "character_name": "Narrator",
      "text": "Is this a contradiction at its roots ?",
      "emotion": "neutral",
      "start_token": 231668,
      "end_token": 231675,
      "sentence_id": 15425,
      "paragraph_id": 0,
      "chapter": 98
    },
    {
      "line_id": "line_000105",
      "character_id": "char_narrator",
      "character_name": "Narrator",
      "text": "In the ancient remains on the main peak of the Hornacis mountain range and its surrounding area , every arrangement and decoration was well - preserved .",
      "emotion": "neutral",
      "start_token": 231676,
      "end_token": 231702,
      "sentence_id": 15426,
      "paragraph_id": 0,
      "chapter": 98
    },
    {
      "line_id": "line_000106",
      "character_id": "char_narrator",
      "character_name": "Narrator",
      "text": "Even the wall murals did n’t have any signs of damage .",
      "emotion": "neutral",
      "start_token": 231703,
      "end_token": 231714,
      "sentence_id": 15427,
      "paragraph_id": 0,
      "chapter": 98
    },
    {
      "line_id": "line_000107",
      "character_id": "char_narrator",
      "character_name": "Narrator",
      "text": "Before it was discovered , there seemed to be no disturbance at all ...",
      "emotion": "neutral",
      "start_token": 231715,
      "end_token": 231728,
      "sentence_id": 15428,
      "paragraph_id": 0,
      "chapter": 98
    },
    {
      "line_id": "line_000108",
      "character_id": "char_narrator",
      "character_name": "Narrator",
      "text": "The table was arranged with cutlery , and there were dried stains of rot on the dining plates ...",
      "emotion": "neutral",
      "start_token": 231729,
      "end_token": 231747,
      "sentence_id": 15429,
      "paragraph_id": 0,
      "chapter": 98
    },
    {
      "line_id": "line_000109",
      "character_id": "char_narrator",
      "character_name": "Narrator",
      "text": "In some rooms , there were half - filled bottles of alcohol that had almost turned into plain water ...",
      "emotion": "neutral",
      "start_token": 231748,
      "end_token": 231767,
      "sentence_id": 15430,
      "paragraph_id": 0,
      "chapter": 98
    },
    {
      "line_id": "line_000110",
      "character_id": "char_narrator",
      "character_name": "Narrator",
      "text": "What happened to the nation ’s people ?",
      "emotion": "neutral",
      "start_token": 231768,
      "end_token": 231775,
      "sentence_id": 15431,
      "paragraph_id": 0,
      "chapter": 98
    },
    {
      "line_id": "line_000111",
      "character_id": "char_narrator",
      "character_name": "Narrator",
      "text": "They seemed to have left their homes in a hurry , without taking anything with them , and they never returned .",
      "emotion": "neutral",
      "start_token": 231776,
      "end_token": 231797,
      "sentence_id": 15432,
      "paragraph_id": 0,
      "chapter": 98
    },
    {
      "line_id": "line_000112",
      "character_id": "char_narrator",
      "character_name": "Narrator",
      "text": "Considering how there are no burial grounds , this only makes it weirder .",
      "emotion": "neutral",
      "start_token": 231798,
      "end_token": 231811,
      "sentence_id": 15433,
      "paragraph_id": 0,
      "chapter": 98
    },
    {
      "line_id": "line_000113",
      "character_id": "char_narrator",
      "character_name": "Narrator",
      "text": "The author , Mr. Joseph , also mentioned that when he first discovered the remains , he even had the belief that the people residing there had just vanished all of a sudden .",
      "emotion": "neutral",
      "start_token": 231812,
      "end_token": 231845,
      "sentence_id": 15434,
      "paragraph_id": 0,
      "chapter": 98
    },
    {
      "line_id": "line_000114",
      "character_id": "char_417",
      "character_name": "Klein",
      "text": "Klein stopped writing and cast his gaze at an illustration .",
      "emotion": "neutral",
      "start_token": 231846,
      "end_token": 231856,
      "sentence_id": 15435,
      "paragraph_id": 0,
      "chapter": 98
    },
    {
      "line_id": "line_000115",
      "character_id": "char_narrator",
      "character_name": "Narrator",
      "text": "On John Joseph ’s third visit to the main peak of the Hornacis mountain range , he had used a new camera model to shoot a monochrome photograph .",
      "emotion": "neutral",
      "start_token": 231857,
      "end_token": 231885,
      "sentence_id": 15436,
      "paragraph_id": 0,
      "chapter": 98
    },
    {
      "line_id": "line_000116",
      "character_id": "char_narrator",
      "character_name": "Narrator",
      "text": "In the photo , the lofty palace had a collapsed wall and was overgrown with weeds .",
      "emotion": "neutral",
      "start_token": 231886,
      "end_token": 231902,
      "sentence_id": 15437,
      "paragraph_id": 0,
      "chapter": 98
    },
    {
      "line_id": "line_000117",
      "character_id": "char_narrator",
      "character_name": "Narrator",
      "text": "It followed a grandeur style for its design .",
      "emotion": "neutral",
      "start_token": 231903,
      "end_token": 231911,
      "sentence_id": 15438,
      "paragraph_id": 0,
      "chapter": 98
    },
    {
      "line_id": "line_000118",
      "character_id": "char_narrator",
      "character_name": "Narrator",
      "text": "When he flipped to the photograph , Klein ’s first thought was that of the palace he had seen in his dream .",
      "emotion": "neutral",
      "start_token": 231912,
      "end_token": 231934,
      "sentence_id": 15439,
      "paragraph_id": 0,
      "chapter": 98
    },
    {
      "line_id": "line_000119",
      "character_id": "char_narrator",
      "character_name": "Narrator",
      "text": "The two styles were identical .",
      "emotion": "neutral",
      "start_token": 231935,
      "end_token": 231940,
      "sentence_id": 15440,
      "paragraph_id": 0,
      "chapter": 98
    },
    {
      "line_id": "line_000120",
      "character_id": "char_narrator",
      "character_name": "Narrator",
      "text": "The only difference was that the one he had dreamed of was on a peak and it was way more magnificent .",
      "emotion": "neutral",
      "start_token": 231941,
      "end_token": 231962,
      "sentence_id": 15441,
      "paragraph_id": 0,
      "chapter": 98
    },
    {
      "line_id": "line_000121",
      "character_id": "char_narrator",
      "character_name": "Narrator",
      "text": "It also had a huge chair — a seat of honor — that looked like it did n’t seat a human .",
      "emotion": "neutral",
      "start_token": 231963,
      "end_token": 231984,
      "sentence_id": 15442,
      "paragraph_id": 0,
      "chapter": 98
    },
    {
      "line_id": "line_000122",
      "character_id": "char_narrator",
      "character_name": "Narrator",
      "text": "Countless translucent maggots clustered together and squirmed slowly beneath the chair .",
      "emotion": "neutral",
      "start_token": 231985,
      "end_token": 231996,
      "sentence_id": 15443,
      "paragraph_id": 0,
      "chapter": 98
    },
    {
      "line_id": "line_000123",
      "character_id": "char_000",
      "character_name": "Character_10000",
      "text": "I can confirm that my dream is related to the ancient remains on the main peak of the Hornacis mountain range ...",
      "emotion": "joy",
      "start_token": 231997,
      "end_token": 232018,
      "sentence_id": 15444,
      "paragraph_id": 0,
      "chapter": 98
    },
    {
      "line_id": "line_000124",
      "character_id": "char_narrator",
      "character_name": "Narrator",
      "text": "That should be the Nation of the Evernight which was referenced in the Antigonus family ’s notebook ...",
      "emotion": "neutral",
      "start_token": 232019,
      "end_token": 232036,
      "sentence_id": 15445,
      "paragraph_id": 0,
      "chapter": 98
    },
    {
      "line_id": "line_000125",
      "character_id": "char_417",
      "character_name": "Klein",
      "text": "Klein nodded slightly and closed the book .",
      "emotion": "neutral",
      "start_token": 232037,
      "end_token": 232044,
      "sentence_id": 15446,
      "paragraph_id": 0,
      "chapter": 98
    },
    {
      "line_id": "line_000126",
      "character_id": "char_narrator",
      "character_name": "Narrator",
      "text": "At that moment , Azik , who was sitting opposite him touched the inconspicuous mole under his right ear and said , “ How was it ?",
      "emotion": "neutral",
      "start_token": 232045,
      "end_token": 232071,
      "sentence_id": 15447,
      "paragraph_id": 0,
      "chapter": 98
    },
    {
      "line_id": "line_000127",
      "character_id": "char_narrator",
      "character_name": "Narrator",
      "text": "Found anything ? ” “ Quite a bit .",
      "emotion": "neutral",
      "start_token": 232072,
      "end_token": 232080,
      "sentence_id": 15448,
      "paragraph_id": 0,
      "chapter": 98
    },
    {
      "line_id": "line_000128",
      "character_id": "char_narrator",
      "character_name": "Narrator",
      "text": "Take a look , I ’ve written so many pages of notes . ”",
      "emotion": "neutral",
      "start_token": 232081,
      "end_token": 232094,
      "sentence_id": 15449,
      "paragraph_id": 0,
      "chapter": 98
    },
    {
      "line_id": "line_000129",
      "character_id": "char_417",
      "character_name": "Klein",
      "text": "Klein pointed at the table and smiled .",
      "emotion": "neutral",
      "start_token": 232095,
      "end_token": 232102,
      "sentence_id": 15450,
      "paragraph_id": 0,
      "chapter": 98
    },
    {
      "line_id": "line_000130",
      "character_id": "char_narrator",
      "character_name": "Narrator",
      "text": "“ I do n’t understand why you ’re suddenly so interested in this matter . ”",
      "emotion": "curious",
      "start_token": 232103,
      "end_token": 232118,
      "sentence_id": 15451,
      "paragraph_id": 0,
      "chapter": 98
    },
    {
      "line_id": "line_000131",
      "character_id": "char_narrator",
      "character_name": "Narrator",
      "text": "Azik sighed and said , “ Klein , when I was studying at the Backlund University , I had dabbled with some divination and did quite a bit of research on that .",
      "emotion": "neutral",
      "start_token": 232119,
      "end_token": 232151,
      "sentence_id": 15452,
      "paragraph_id": 0,
      "chapter": 98
    },
    {
      "line_id": "line_000132",
      "character_id": "char_narrator",
      "character_name": "Narrator",
      "text": "Well , I discovered that there is disharmony ... in your fate . ”",
      "emotion": "neutral",
      "start_token": 232152,
      "end_token": 232165,
      "sentence_id": 15453,
      "paragraph_id": 0,
      "chapter": 98
    },
    {
      "line_id": "line_000133",
      "character_id": "char_narrator",
      "character_name": "Narrator",
      "text": "What ?",
      "emotion": "neutral",
      "start_token": 232166,
      "end_token": 232167,
      "sentence_id": 15454,
      "paragraph_id": 0,
      "chapter": 98
    },
    {
      "line_id": "line_000134",
      "character_id": "char_narrator",
      "character_name": "Narrator",
      "text": "Divination ?",
      "emotion": "neutral",
      "start_token": 232168,
      "end_token": 232169,
      "sentence_id": 15455,
      "paragraph_id": 0,
      "chapter": 98
    },
    {
      "line_id": "line_000135",
      "character_id": "char_000",
      "character_name": "Character_10000",
      "text": "Are you talking to me about divination ?",
      "emotion": "neutral",
      "start_token": 232170,
      "end_token": 232177,
      "sentence_id": 15456,
      "paragraph_id": 0,
      "chapter": 98
    },
    {
      "line_id": "line_000136",
      "character_id": "char_narrator",
      "character_name": "Narrator",
      "text": "As a Seer , Klein looked at Azik the academic in amusement .",
      "emotion": "neutral",
      "start_token": 232178,
      "end_token": 232190,
      "sentence_id": 15457,
      "paragraph_id": 0,
      "chapter": 98
    },
    {
      "line_id": "line_000137",
      "character_id": "char_narrator",
      "character_name": "Narrator",
      "text": "“ How is it disharmonious ? ” Azik thought for a moment .",
      "emotion": "neutral",
      "start_token": 232191,
      "end_token": 232203,
      "sentence_id": 15458,
      "paragraph_id": 0,
      "chapter": 98
    },
    {
      "line_id": "line_000138",
      "character_id": "char_narrator",
      "character_name": "Narrator",
      "text": "“ Have you encountered many strange coincidences in the past two months ? ” “ Coincidences ? ”",
      "emotion": "neutral",
      "start_token": 232204,
      "end_token": 232221,
      "sentence_id": 15459,
      "paragraph_id": 0,
      "chapter": 98
    },
    {
      "line_id": "line_000139",
      "character_id": "char_narrator",
      "character_name": "Narrator",
      "text": "As he was indebted to Mr. Azik , Klein did n’t dispute his question as he subconsciously began thinking .",
      "emotion": "neutral",
      "start_token": 232222,
      "end_token": 232241,
      "sentence_id": 15460,
      "paragraph_id": 0,
      "chapter": 98
    },
    {
      "line_id": "line_000140",
      "character_id": "char_narrator",
      "character_name": "Narrator",
      "text": "If we are talking about coincidences , the most obvious matter was when we were after kidnappers .",
      "emotion": "neutral",
      "start_token": 232242,
      "end_token": 232259,
      "sentence_id": 15461,
      "paragraph_id": 0,
      "chapter": 98
    },
    {
      "line_id": "line_000141",
      "character_id": "char_narrator",
      "character_name": "Narrator",
      "text": "We actually managed to find clues of the Antigonus family ’s notebook that was lost for days in the room opposite the kidnappers .",
      "emotion": "confusion",
      "start_token": 232260,
      "end_token": 232283,
      "sentence_id": 15462,
      "paragraph_id": 0,
      "chapter": 98
    },
    {
      "line_id": "line_000142",
      "character_id": "char_narrator",
      "character_name": "Narrator",
      "text": "Also , Ray Bieber did n’t flee from Tingen in a hurry ; instead , he found a place to digest the power bestowed by the notebook , allowing for Sealed Artifact 2 - 049 to track him down easily .",
      "emotion": "neutral",
      "start_token": 232284,
      "end_token": 232324,
      "sentence_id": 15463,
      "paragraph_id": 0,
      "chapter": 98
    },
    {
      "line_id": "line_000143",
      "character_id": "char_narrator",
      "character_name": "Narrator",
      "text": "That seemed to be against common sense .",
      "emotion": "neutral",
      "start_token": 232325,
      "end_token": 232332,
      "sentence_id": 15464,
      "paragraph_id": 0,
      "chapter": 98
    },
    {
      "line_id": "line_000144",
      "character_id": "char_narrator",
      "character_name": "Narrator",
      "text": "Although Aiur Harson gave a reasonable explanation , I always had a nagging feeling that it was somewhat coincidental ...",
      "emotion": "neutral",
      "start_token": 232333,
      "end_token": 232352,
      "sentence_id": 15465,
      "paragraph_id": 0,
      "chapter": 98
    },
    {
      "line_id": "line_000145",
      "character_id": "char_narrator",
      "character_name": "Narrator",
      "text": "Oh , Selena had stolen a glance at Hanass Vincent ’s secret incantations , but she held back till her birthday dinner banquet to try it out , and I happened to discover it , which is quite a coincidence too .",
      "emotion": "neutral",
      "start_token": 232353,
      "end_token": 232394,
      "sentence_id": 15466,
      "paragraph_id": 0,
      "chapter": 98
    },
    {
      "line_id": "line_000146",
      "character_id": "char_narrator",
      "character_name": "Narrator",
      "text": "Otherwise , Hanass Vincent would n’t have been the only one to die so suddenly ...",
      "emotion": "neutral",
      "start_token": 232395,
      "end_token": 232410,
      "sentence_id": 15467,
      "paragraph_id": 0,
      "chapter": 98
    },
    {
      "line_id": "line_000147",
      "character_id": "char_417",
      "character_name": "Klein",
      "text": "Klein thought about it seriously for a few minutes and said , “ There are three .",
      "emotion": "neutral",
      "start_token": 232411,
      "end_token": 232427,
      "sentence_id": 15468,
      "paragraph_id": 0,
      "chapter": 98
    },
    {
      "line_id": "line_000148",
      "character_id": "char_narrator",
      "character_name": "Narrator",
      "text": "Neither too many , nor too frequent .",
      "emotion": "neutral",
      "start_token": 232428,
      "end_token": 232435,
      "sentence_id": 15469,
      "paragraph_id": 0,
      "chapter": 98
    },
    {
      "line_id": "line_000149",
      "character_id": "char_narrator",
      "character_name": "Narrator",
      "text": "Furthermore , there was nothing that indicated someone ’s involvement and guidance . ”",
      "emotion": "neutral",
      "start_token": 232436,
      "end_token": 232449,
      "sentence_id": 15470,
      "paragraph_id": 0,
      "chapter": 98
    },
    {
      "line_id": "line_000150",
      "character_id": "char_narrator",
      "character_name": "Narrator",
      "text": "Azik nodded slightly .",
      "emotion": "neutral",
      "start_token": 232450,
      "end_token": 232453,
      "sentence_id": 15471,
      "paragraph_id": 0,
      "chapter": 98
    },
    {
      "line_id": "line_000151",
      "character_id": "char_narrator",
      "character_name": "Narrator",
      "text": "“ As Emperor Roselle once said , a single coincidence is encountered by anyone .",
      "emotion": "neutral",
      "start_token": 232454,
      "end_token": 232468,
      "sentence_id": 15472,
      "paragraph_id": 0,
      "chapter": 98
    },
    {
      "line_id": "line_000152",
      "character_id": "char_narrator",
      "character_name": "Narrator",
      "text": "Twice is still normal .",
      "emotion": "neutral",
      "start_token": 232469,
      "end_token": 232473,
      "sentence_id": 15473,
      "paragraph_id": 0,
      "chapter": 98
    },
    {
      "line_id": "line_000153",
      "character_id": "char_narrator",
      "character_name": "Narrator",
      "text": "Thrice is when one should consider what internal factors are influencing those coincidences . ” “ Can you tell me anything else ? ”",
      "emotion": "neutral",
      "start_token": 232474,
      "end_token": 232497,
      "sentence_id": 15474,
      "paragraph_id": 0,
      "chapter": 98
    },
    {
      "line_id": "line_000154",
      "character_id": "char_417",
      "character_name": "Klein",
      "text": "Klein probed .",
      "emotion": "neutral",
      "start_token": 232498,
      "end_token": 232500,
      "sentence_id": 15475,
      "paragraph_id": 0,
      "chapter": 98
    },
    {
      "line_id": "line_000155",
      "character_id": "char_narrator",
      "character_name": "Narrator",
      "text": "Azik laughed and shook his head .",
      "emotion": "neutral",
      "start_token": 232501,
      "end_token": 232507,
      "sentence_id": 15476,
      "paragraph_id": 0,
      "chapter": 98
    },
    {
      "line_id": "line_000156",
      "character_id": "char_narrator",
      "character_name": "Narrator",
      "text": "“ I can only tell that there ’s some disharmony , but nothing else .",
      "emotion": "neutral",
      "start_token": 232508,
      "end_token": 232522,
      "sentence_id": 15477,
      "paragraph_id": 0,
      "chapter": 98
    },
    {
      "line_id": "line_000157",
      "character_id": "char_narrator",
      "character_name": "Narrator",
      "text": "You have to understand that I ’m not a real seer . ” Is n’t that basically equal to saying nothing ...",
      "emotion": "neutral",
      "start_token": 232523,
      "end_token": 232544,
      "sentence_id": 15478,
      "paragraph_id": 0,
      "chapter": 98
    },
    {
      "line_id": "line_000158",
      "character_id": "char_narrator",
      "character_name": "Narrator",
      "text": "Mr. Azik is quite odd ...",
      "emotion": "neutral",
      "start_token": 232545,
      "end_token": 232550,
      "sentence_id": 15479,
      "paragraph_id": 0,
      "chapter": 98
    },
    {
      "line_id": "line_000159",
      "character_id": "char_narrator",
      "character_name": "Narrator",
      "text": "He ’s playing a charlatan in front of a charlatan like me ...",
      "emotion": "neutral",
      "start_token": 232551,
      "end_token": 232563,
      "sentence_id": 15480,
      "paragraph_id": 0,
      "chapter": 98
    },
    {
      "line_id": "line_000160",
      "character_id": "char_417",
      "character_name": "Klein",
      "text": "Klein let out a breath , seizing the moment when Azik stood up , he pinched his glabella and activated his Spirit Vision .",
      "emotion": "neutral",
      "start_token": 232564,
      "end_token": 232587,
      "sentence_id": 15481,
      "paragraph_id": 0,
      "chapter": 98
    },
    {
      "line_id": "line_000161",
      "character_id": "char_narrator",
      "character_name": "Narrator",
      "text": "When he looked over , Azik ’s aura fully appeared before his eyes and everything seemed fairly normal .",
      "emotion": "neutral",
      "start_token": 232588,
      "end_token": 232606,
      "sentence_id": 15482,
      "paragraph_id": 0,
      "chapter": 98
    },
    {
      "line_id": "line_000162",
      "character_id": "char_narrator",
      "character_name": "Narrator",
      "text": "Unfortunately , I can only see the Ether Body and Astral Projection of a person above the gray fog ...",
      "emotion": "neutral",
      "start_token": 232607,
      "end_token": 232626,
      "sentence_id": 15483,
      "paragraph_id": 0,
      "chapter": 98
    },
    {
      "line_id": "line_000163",
      "character_id": "char_417",
      "character_name": "Klein",
      "text": "Klein thought carefreely as he tapped his glabella again whilst standing up .",
      "emotion": "neutral",
      "start_token": 232627,
      "end_token": 232639,
      "sentence_id": 15484,
      "paragraph_id": 0,
      "chapter": 98
    }
  ]
}