{
  "chapter": 180,
  "total_lines": 125,
  "characters_in_chapter": [
    "char_narrator",
    "char_430",
    "char_432",
    "char_417",
    "char_762",
    "char_000"
  ],
  "character_line_counts": {
    "char_narrator": 85,
    "char_430": 9,
    "char_432": 3,
    "char_417": 22,
    "char_762": 4,
    "char_000": 2
  },
  "emotion_distribution": {
    "neutral": 110,
    "curious": 2,
    "surprise": 3,
    "anger": 5,
    "fear": 3,
    "confusion": 1,
    "pain": 1
  },
  "lines": [
    {
      "line_id": "line_000001",
      "character_id": "char_narrator",
      "character_name": "Narrator",
      "text": "Upon hearing The Fool ’s question , Audrey perked up her ears and entered her Spectator state .",
      "emotion": "neutral",
      "start_token": 413098,
      "end_token": 413115,
      "sentence_id": 26610,
      "paragraph_id": 0,
      "chapter": 180
    },
    {
      "line_id": "line_000002",
      "character_id": "char_430",
      "character_name": "Audrey",
      "text": "She waited for The Sun to answer .",
      "emotion": "neutral",
      "start_token": 413116,
      "end_token": 413123,
      "sentence_id": 26611,
      "paragraph_id": 0,
      "chapter": 180
    },
    {
      "line_id": "line_000003",
      "character_id": "char_430",
      "character_name": "Audrey",
      "text": "She had always been curious about where the City of Silver was and what was so special about that place , but she could n’t bring herself to ask .",
      "emotion": "curious",
      "start_token": 413124,
      "end_token": 413153,
      "sentence_id": 26612,
      "paragraph_id": 0,
      "chapter": 180
    },
    {
      "line_id": "line_000004",
      "character_id": "char_narrator",
      "character_name": "Narrator",
      "text": "It touched upon his privacy after all .",
      "emotion": "neutral",
      "start_token": 413154,
      "end_token": 413161,
      "sentence_id": 26613,
      "paragraph_id": 0,
      "chapter": 180
    },
    {
      "line_id": "line_000005",
      "character_id": "char_narrator",
      "character_name": "Narrator",
      "text": "At that moment , Mr. Fool was asking personally .",
      "emotion": "neutral",
      "start_token": 413162,
      "end_token": 413171,
      "sentence_id": 26614,
      "paragraph_id": 0,
      "chapter": 180
    },
    {
      "line_id": "line_000006",
      "character_id": "char_narrator",
      "character_name": "Narrator",
      "text": "It was like finishing the first volume of an outstanding detective novel she had been reading for a long time , and she finally had the chance to buy the next volume !",
      "emotion": "neutral",
      "start_token": 413172,
      "end_token": 413204,
      "sentence_id": 26615,
      "paragraph_id": 0,
      "chapter": 180
    },
    {
      "line_id": "line_000007",
      "character_id": "char_narrator",
      "character_name": "Narrator",
      "text": "The Sun ’s answer did n’t disappoint her .",
      "emotion": "neutral",
      "start_token": 413205,
      "end_token": 413213,
      "sentence_id": 26616,
      "paragraph_id": 0,
      "chapter": 180
    },
    {
      "line_id": "line_000008",
      "character_id": "char_narrator",
      "character_name": "Narrator",
      "text": "They did n’t believe in the mainstream seven orthodox deities , nor did they believe in Death as the Southern Continent did .",
      "emotion": "neutral",
      "start_token": 413214,
      "end_token": 413236,
      "sentence_id": 26617,
      "paragraph_id": 0,
      "chapter": 180
    },
    {
      "line_id": "line_000009",
      "character_id": "char_narrator",
      "character_name": "Narrator",
      "text": "They also did n’t believe in the hidden existences , evil gods or devils — Primordial Demoness , Hidden Sage , Dark Side of the Universe , Chained God , or the True Creator — which The Hanged Man had told her before .",
      "emotion": "neutral",
      "start_token": 413237,
      "end_token": 413280,
      "sentence_id": 26618,
      "paragraph_id": 0,
      "chapter": 180
    },
    {
      "line_id": "line_000010",
      "character_id": "char_narrator",
      "character_name": "Narrator",
      "text": "The City of Silver is really special !",
      "emotion": "neutral",
      "start_token": 413281,
      "end_token": 413288,
      "sentence_id": 26619,
      "paragraph_id": 0,
      "chapter": 180
    },
    {
      "line_id": "line_000011",
      "character_id": "char_narrator",
      "character_name": "Narrator",
      "text": "They actually worship the Creator Himself !",
      "emotion": "neutral",
      "start_token": 413289,
      "end_token": 413295,
      "sentence_id": 26620,
      "paragraph_id": 0,
      "chapter": 180
    },
    {
      "line_id": "line_000012",
      "character_id": "char_narrator",
      "character_name": "Narrator",
      "text": "This is the primordial worship that Mr. Hanged Man described , right ?",
      "emotion": "neutral",
      "start_token": 413296,
      "end_token": 413308,
      "sentence_id": 26621,
      "paragraph_id": 0,
      "chapter": 180
    },
    {
      "line_id": "line_000013",
      "character_id": "char_narrator",
      "character_name": "Narrator",
      "text": "Hmm , the description of omnipotence is a little strange ...",
      "emotion": "neutral",
      "start_token": 413309,
      "end_token": 413319,
      "sentence_id": 26622,
      "paragraph_id": 0,
      "chapter": 180
    },
    {
      "line_id": "line_000014",
      "character_id": "char_430",
      "character_name": "Audrey",
      "text": "Audrey stole a glance at The Hanged Man subconsciously and realized that he was nodding slightly .",
      "emotion": "neutral",
      "start_token": 413320,
      "end_token": 413336,
      "sentence_id": 26623,
      "paragraph_id": 0,
      "chapter": 180
    },
    {
      "line_id": "line_000015",
      "character_id": "char_narrator",
      "character_name": "Narrator",
      "text": "Klein was n’t surprised at all .",
      "emotion": "surprise",
      "start_token": 413337,
      "end_token": 413343,
      "sentence_id": 26624,
      "paragraph_id": 0,
      "chapter": 180
    },
    {
      "line_id": "line_000016",
      "character_id": "char_narrator",
      "character_name": "Narrator",
      "text": "He purposely chuckled and asked in reply , “ Even though He abandoned you ? ” Abandoned ?",
      "emotion": "neutral",
      "start_token": 413344,
      "end_token": 413361,
      "sentence_id": 26625,
      "paragraph_id": 0,
      "chapter": 180
    },
    {
      "line_id": "line_000017",
      "character_id": "char_narrator",
      "character_name": "Narrator",
      "text": "The Creator abandoned the City of Silver ?",
      "emotion": "neutral",
      "start_token": 413362,
      "end_token": 413369,
      "sentence_id": 26626,
      "paragraph_id": 0,
      "chapter": 180
    },
    {
      "line_id": "line_000018",
      "character_id": "char_432",
      "character_name": "Alger",
      "text": "Alger was shocked .",
      "emotion": "surprise",
      "start_token": 413370,
      "end_token": 413373,
      "sentence_id": 26627,
      "paragraph_id": 0,
      "chapter": 180
    },
    {
      "line_id": "line_000019",
      "character_id": "char_narrator",
      "character_name": "Narrator",
      "text": "Suddenly when he suddenly made the connection regarding a particular term .",
      "emotion": "anger",
      "start_token": 413374,
      "end_token": 413385,
      "sentence_id": 26628,
      "paragraph_id": 0,
      "chapter": 180
    },
    {
      "line_id": "line_000020",
      "character_id": "char_narrator",
      "character_name": "Narrator",
      "text": "The Forsaken Land of the Gods !",
      "emotion": "neutral",
      "start_token": 413386,
      "end_token": 413392,
      "sentence_id": 26629,
      "paragraph_id": 0,
      "chapter": 180
    },
    {
      "line_id": "line_000021",
      "character_id": "char_narrator",
      "character_name": "Narrator",
      "text": "In the confidential information of the Church of the Lord of Storms , at the security clearance level that Alger , who was Captain — equivalent to the Bishop level — could access , the Forsaken Land of the Gods had always only been a name with no actual description .",
      "emotion": "neutral",
      "start_token": 413393,
      "end_token": 413443,
      "sentence_id": 26630,
      "paragraph_id": 0,
      "chapter": 180
    },
    {
      "line_id": "line_000022",
      "character_id": "char_narrator",
      "character_name": "Narrator",
      "text": "However , it clearly pointed towards the end of the Sonia Sea .",
      "emotion": "neutral",
      "start_token": 413444,
      "end_token": 413456,
      "sentence_id": 26631,
      "paragraph_id": 0,
      "chapter": 180
    },
    {
      "line_id": "line_000023",
      "character_id": "char_narrator",
      "character_name": "Narrator",
      "text": "From what he knew , even the Cardinals at the core of the church had no idea what the Forsaken Land of the Gods represented .",
      "emotion": "neutral",
      "start_token": 413457,
      "end_token": 413482,
      "sentence_id": 26632,
      "paragraph_id": 0,
      "chapter": 180
    },
    {
      "line_id": "line_000024",
      "character_id": "char_narrator",
      "character_name": "Narrator",
      "text": "But only the leader of the church , the Proxy of the Lord of Storms , knew something about the situation and seemed to be taking charge of the hidden mission to look for the Forsaken Land of the Gods .",
      "emotion": "neutral",
      "start_token": 413483,
      "end_token": 413523,
      "sentence_id": 26633,
      "paragraph_id": 0,
      "chapter": 180
    },
    {
      "line_id": "line_000025",
      "character_id": "char_432",
      "character_name": "Alger",
      "text": "Alger had once made a bold guess when he equated the True Creator ’s holy residence which was promoted by the Aurora Order with the Forsaken Land of the Gods .",
      "emotion": "anger",
      "start_token": 413524,
      "end_token": 413554,
      "sentence_id": 26634,
      "paragraph_id": 0,
      "chapter": 180
    },
    {
      "line_id": "line_000026",
      "character_id": "char_432",
      "character_name": "Alger",
      "text": "But , unfortunately , The Fool had n’t confirmed his guess , so he could n’t be sure .",
      "emotion": "neutral",
      "start_token": 413555,
      "end_token": 413573,
      "sentence_id": 26635,
      "paragraph_id": 0,
      "chapter": 180
    },
    {
      "line_id": "line_000027",
      "character_id": "char_narrator",
      "character_name": "Narrator",
      "text": "Now , he was shocked and surprised to find that the Tarot Club member using The Sun as his code name was very likely from the Forsaken Land of the Gods !",
      "emotion": "surprise",
      "start_token": 413574,
      "end_token": 413605,
      "sentence_id": 26636,
      "paragraph_id": 0,
      "chapter": 180
    },
    {
      "line_id": "line_000028",
      "character_id": "char_narrator",
      "character_name": "Narrator",
      "text": "Mr. Fool knew where the Forsaken Land of the Gods was all this time , and he could pull someone from there to be a member of the Gathering !",
      "emotion": "neutral",
      "start_token": 413606,
      "end_token": 413635,
      "sentence_id": 26637,
      "paragraph_id": 0,
      "chapter": 180
    },
    {
      "line_id": "line_000029",
      "character_id": "char_narrator",
      "character_name": "Narrator",
      "text": "This is a hidden place that the Church of the Lord of Storms has been trying to find to no avail !",
      "emotion": "neutral",
      "start_token": 413636,
      "end_token": 413657,
      "sentence_id": 26638,
      "paragraph_id": 0,
      "chapter": 180
    },
    {
      "line_id": "line_000030",
      "character_id": "char_narrator",
      "character_name": "Narrator",
      "text": "Alger looked at The Fool who was seated in the seat of honor at the end of the ancient long bronze table in horror .",
      "emotion": "fear",
      "start_token": 413658,
      "end_token": 413682,
      "sentence_id": 26639,
      "paragraph_id": 0,
      "chapter": 180
    },
    {
      "line_id": "line_000031",
      "character_id": "char_narrator",
      "character_name": "Narrator",
      "text": "He could only see that he was leaning back in his chair in silence , engulfed by the thick fog .",
      "emotion": "neutral",
      "start_token": 413683,
      "end_token": 413703,
      "sentence_id": 26640,
      "paragraph_id": 0,
      "chapter": 180
    },
    {
      "line_id": "line_000032",
      "character_id": "char_430",
      "character_name": "Audrey",
      "text": "Audrey was n’t particularly moved about it .",
      "emotion": "neutral",
      "start_token": 413704,
      "end_token": 413711,
      "sentence_id": 26641,
      "paragraph_id": 0,
      "chapter": 180
    },
    {
      "line_id": "line_000033",
      "character_id": "char_narrator",
      "character_name": "Narrator",
      "text": "The only time that she had heard about the Forsaken Land of the Gods was from The Hanged Man ’s question .",
      "emotion": "neutral",
      "start_token": 413712,
      "end_token": 413733,
      "sentence_id": 26642,
      "paragraph_id": 0,
      "chapter": 180
    },
    {
      "line_id": "line_000034",
      "character_id": "char_430",
      "character_name": "Audrey",
      "text": "She was n’t particularly interested , so she failed to associate it to anything from what Mr. Fool said earlier .",
      "emotion": "curious",
      "start_token": 413734,
      "end_token": 413754,
      "sentence_id": 26643,
      "paragraph_id": 0,
      "chapter": 180
    },
    {
      "line_id": "line_000035",
      "character_id": "char_narrator",
      "character_name": "Narrator",
      "text": "The City of Silver has the legend about being abandoned by the Creator ...",
      "emotion": "neutral",
      "start_token": 413755,
      "end_token": 413768,
      "sentence_id": 26644,
      "paragraph_id": 0,
      "chapter": 180
    },
    {
      "line_id": "line_000036",
      "character_id": "char_narrator",
      "character_name": "Narrator",
      "text": "Huh , Mr. Hanged Man seems to be deeply affected ...",
      "emotion": "neutral",
      "start_token": 413769,
      "end_token": 413779,
      "sentence_id": 26645,
      "paragraph_id": 0,
      "chapter": 180
    },
    {
      "line_id": "line_000037",
      "character_id": "char_narrator",
      "character_name": "Narrator",
      "text": "What is he amazed and afraid of ?",
      "emotion": "fear",
      "start_token": 413780,
      "end_token": 413787,
      "sentence_id": 26646,
      "paragraph_id": 0,
      "chapter": 180
    },
    {
      "line_id": "line_000038",
      "character_id": "char_430",
      "character_name": "Audrey",
      "text": "Audrey nodded in puzzlement as she remembered the details of the moment .",
      "emotion": "neutral",
      "start_token": 413788,
      "end_token": 413800,
      "sentence_id": 26647,
      "paragraph_id": 0,
      "chapter": 180
    },
    {
      "line_id": "line_000039",
      "character_id": "char_narrator",
      "character_name": "Narrator",
      "text": "“ Yes , we believe that we will regain the Lord ’s favor in the end .",
      "emotion": "neutral",
      "start_token": 413801,
      "end_token": 413817,
      "sentence_id": 26648,
      "paragraph_id": 0,
      "chapter": 180
    },
    {
      "line_id": "line_000040",
      "character_id": "char_narrator",
      "character_name": "Narrator",
      "text": "Perhaps , it will be on the day the sun rises again , ” Derrick Berg answered in an uncertain tone .",
      "emotion": "confusion",
      "start_token": 413818,
      "end_token": 413839,
      "sentence_id": 26649,
      "paragraph_id": 0,
      "chapter": 180
    },
    {
      "line_id": "line_000041",
      "character_id": "char_narrator",
      "character_name": "Narrator",
      "text": "“ We were once ruled by the giants ’ royal family , and we worshiped the Giant King Aurmir .",
      "emotion": "neutral",
      "start_token": 413840,
      "end_token": 413859,
      "sentence_id": 26650,
      "paragraph_id": 0,
      "chapter": 180
    },
    {
      "line_id": "line_000042",
      "character_id": "char_narrator",
      "character_name": "Narrator",
      "text": "Later , we were saved by the Lord and we will never betray the Lord again . ” Ruled by the giants ’ royal family ...",
      "emotion": "neutral",
      "start_token": 413860,
      "end_token": 413885,
      "sentence_id": 26651,
      "paragraph_id": 0,
      "chapter": 180
    },
    {
      "line_id": "line_000043",
      "character_id": "char_narrator",
      "character_name": "Narrator",
      "text": "It really is ancient .",
      "emotion": "neutral",
      "start_token": 413886,
      "end_token": 413890,
      "sentence_id": 26652,
      "paragraph_id": 0,
      "chapter": 180
    },
    {
      "line_id": "line_000044",
      "character_id": "char_narrator",
      "character_name": "Narrator",
      "text": "But it does n’t seem to match ...",
      "emotion": "neutral",
      "start_token": 413891,
      "end_token": 413898,
      "sentence_id": 26653,
      "paragraph_id": 0,
      "chapter": 180
    },
    {
      "line_id": "line_000045",
      "character_id": "char_narrator",
      "character_name": "Narrator",
      "text": "Alger , who had guessed at something , suddenly recalled the description about the Second Epoch in the hidden chapter of The Book of Storms .",
      "emotion": "neutral",
      "start_token": 413899,
      "end_token": 413924,
      "sentence_id": 26654,
      "paragraph_id": 0,
      "chapter": 180
    },
    {
      "line_id": "line_000046",
      "character_id": "char_narrator",
      "character_name": "Narrator",
      "text": "The Second Epoch was also known as humanity ’s Dark Epoch .",
      "emotion": "neutral",
      "start_token": 413925,
      "end_token": 413936,
      "sentence_id": 26655,
      "paragraph_id": 0,
      "chapter": 180
    },
    {
      "line_id": "line_000047",
      "character_id": "char_narrator",
      "character_name": "Narrator",
      "text": "At the time , the sky , ocean , and land were ruled over by dragons , giants , elves , mutants , devils , phoenixes , demonic wolves , and dead spirits .",
      "emotion": "neutral",
      "start_token": 413937,
      "end_token": 413970,
      "sentence_id": 26656,
      "paragraph_id": 0,
      "chapter": 180
    },
    {
      "line_id": "line_000048",
      "character_id": "char_narrator",
      "character_name": "Narrator",
      "text": "But in the end , the Lord of Storms , Eternal Blazing Sun , and the God of Knowledge and Wisdom led humanity into defeating the supernatural creatures and ushered in the beginning of the Third Epoch , the Glorious Era , which was later known as Cataclysm .",
      "emotion": "neutral",
      "start_token": 413971,
      "end_token": 414019,
      "sentence_id": 26657,
      "paragraph_id": 0,
      "chapter": 180
    },
    {
      "line_id": "line_000049",
      "character_id": "char_417",
      "character_name": "Klein",
      "text": "Giant King Aurmir ...",
      "emotion": "neutral",
      "start_token": 414020,
      "end_token": 414023,
      "sentence_id": 26658,
      "paragraph_id": 0,
      "chapter": 180
    },
    {
      "line_id": "line_000050",
      "character_id": "char_417",
      "character_name": "Klein",
      "text": "Klein repeated the name in silence .",
      "emotion": "neutral",
      "start_token": 414024,
      "end_token": 414030,
      "sentence_id": 26659,
      "paragraph_id": 0,
      "chapter": 180
    },
    {
      "line_id": "line_000051",
      "character_id": "char_narrator",
      "character_name": "Narrator",
      "text": "In various legends and myths , it was a great existence on par with the deities .",
      "emotion": "neutral",
      "start_token": 414031,
      "end_token": 414047,
      "sentence_id": 26660,
      "paragraph_id": 0,
      "chapter": 180
    },
    {
      "line_id": "line_000052",
      "character_id": "char_narrator",
      "character_name": "Narrator",
      "text": "Even now , there were still some places that worshiped him .",
      "emotion": "neutral",
      "start_token": 414048,
      "end_token": 414059,
      "sentence_id": 26661,
      "paragraph_id": 0,
      "chapter": 180
    },
    {
      "line_id": "line_000053",
      "character_id": "char_narrator",
      "character_name": "Narrator",
      "text": "Even the most famous and most expensive grape wine in the Intis Republic was named after Aurmir .",
      "emotion": "neutral",
      "start_token": 414060,
      "end_token": 414077,
      "sentence_id": 26662,
      "paragraph_id": 0,
      "chapter": 180
    },
    {
      "line_id": "line_000054",
      "character_id": "char_narrator",
      "character_name": "Narrator",
      "text": "It was said that the Giant King particularly fancied grape wine which was like blood .",
      "emotion": "neutral",
      "start_token": 414078,
      "end_token": 414093,
      "sentence_id": 26663,
      "paragraph_id": 0,
      "chapter": 180
    },
    {
      "line_id": "line_000055",
      "character_id": "char_narrator",
      "character_name": "Narrator",
      "text": "Considering the fact that the Church of the God of Combat is in control of the complete pathway of the Warrior , which once belonged to the giants , can I assume that Aurmir was the ancient God of Combat ?",
      "emotion": "neutral",
      "start_token": 414094,
      "end_token": 414134,
      "sentence_id": 26664,
      "paragraph_id": 0,
      "chapter": 180
    },
    {
      "line_id": "line_000056",
      "character_id": "char_417",
      "character_name": "Klein",
      "text": "Klein guessed .",
      "emotion": "neutral",
      "start_token": 414135,
      "end_token": 414137,
      "sentence_id": 26665,
      "paragraph_id": 0,
      "chapter": 180
    },
    {
      "line_id": "line_000057",
      "character_id": "char_417",
      "character_name": "Klein",
      "text": "He nodded deliberately but did n’t think any further about it .",
      "emotion": "neutral",
      "start_token": 414138,
      "end_token": 414149,
      "sentence_id": 26666,
      "paragraph_id": 0,
      "chapter": 180
    },
    {
      "line_id": "line_000058",
      "character_id": "char_417",
      "character_name": "Klein",
      "text": "He then asked calmly , “ Do you still offer sacrifices to this omnipotent God ? ” “ Yes , we still do .",
      "emotion": "neutral",
      "start_token": 414150,
      "end_token": 414173,
      "sentence_id": 26667,
      "paragraph_id": 0,
      "chapter": 180
    },
    {
      "line_id": "line_000059",
      "character_id": "char_narrator",
      "character_name": "Narrator",
      "text": "But since the day we were abandoned , we have never gotten any response . ”",
      "emotion": "neutral",
      "start_token": 414174,
      "end_token": 414189,
      "sentence_id": 26668,
      "paragraph_id": 0,
      "chapter": 180
    },
    {
      "line_id": "line_000060",
      "character_id": "char_762",
      "character_name": "Derrick",
      "text": "Derrick ’s voice had a hint of unconcealed pain .",
      "emotion": "pain",
      "start_token": 414190,
      "end_token": 414199,
      "sentence_id": 26669,
      "paragraph_id": 0,
      "chapter": 180
    },
    {
      "line_id": "line_000061",
      "character_id": "char_417",
      "character_name": "Klein",
      "text": "Klein leaned against the back of his chair leisurely .",
      "emotion": "neutral",
      "start_token": 414200,
      "end_token": 414209,
      "sentence_id": 26670,
      "paragraph_id": 0,
      "chapter": 180
    },
    {
      "line_id": "line_000062",
      "character_id": "char_417",
      "character_name": "Klein",
      "text": "He half - closed his eyes and said , “ Describe the process of your offering ritual in detail . ”",
      "emotion": "neutral",
      "start_token": 414210,
      "end_token": 414230,
      "sentence_id": 26671,
      "paragraph_id": 0,
      "chapter": 180
    },
    {
      "line_id": "line_000063",
      "character_id": "char_narrator",
      "character_name": "Narrator",
      "text": "Does Mr. Fool want to figure out the truth behind the City of Silver ’s abandonment ?",
      "emotion": "neutral",
      "start_token": 414231,
      "end_token": 414247,
      "sentence_id": 26672,
      "paragraph_id": 0,
      "chapter": 180
    },
    {
      "line_id": "line_000064",
      "character_id": "char_narrator",
      "character_name": "Narrator",
      "text": "Or does He want to determine if the Creator still exists ?",
      "emotion": "neutral",
      "start_token": 414248,
      "end_token": 414259,
      "sentence_id": 26673,
      "paragraph_id": 0,
      "chapter": 180
    },
    {
      "line_id": "line_000065",
      "character_id": "char_narrator",
      "character_name": "Narrator",
      "text": "Alger suddenly felt a shock through his body and he quivered .",
      "emotion": "neutral",
      "start_token": 414260,
      "end_token": 414271,
      "sentence_id": 26674,
      "paragraph_id": 0,
      "chapter": 180
    },
    {
      "line_id": "line_000066",
      "character_id": "char_narrator",
      "character_name": "Narrator",
      "text": "Not only was he afraid , but he was also excited too .",
      "emotion": "fear",
      "start_token": 414272,
      "end_token": 414284,
      "sentence_id": 26675,
      "paragraph_id": 0,
      "chapter": 180
    },
    {
      "line_id": "line_000067",
      "character_id": "char_narrator",
      "character_name": "Narrator",
      "text": "This was because he felt he was being made privy to the secrets between deities !",
      "emotion": "anger",
      "start_token": 414285,
      "end_token": 414300,
      "sentence_id": 26676,
      "paragraph_id": 0,
      "chapter": 180
    },
    {
      "line_id": "line_000068",
      "character_id": "char_narrator",
      "character_name": "Narrator",
      "text": "That made him feel like he had been elevated to a whole new level !",
      "emotion": "anger",
      "start_token": 414301,
      "end_token": 414315,
      "sentence_id": 26677,
      "paragraph_id": 0,
      "chapter": 180
    },
    {
      "line_id": "line_000069",
      "character_id": "char_narrator",
      "character_name": "Narrator",
      "text": "I ’ve been chasing after power , after strength .",
      "emotion": "neutral",
      "start_token": 414316,
      "end_token": 414325,
      "sentence_id": 26678,
      "paragraph_id": 0,
      "chapter": 180
    },
    {
      "line_id": "line_000070",
      "character_id": "char_narrator",
      "character_name": "Narrator",
      "text": "Did n’t",
      "emotion": "neutral",
      "start_token": 414326,
      "end_token": 414327,
      "sentence_id": 26679,
      "paragraph_id": 0,
      "chapter": 180
    },
    {
      "line_id": "line_000071",
      "character_id": "char_narrator",
      "character_name": "Narrator",
      "text": "I do it to achieve this kind of feeling ?",
      "emotion": "neutral",
      "start_token": 414328,
      "end_token": 414337,
      "sentence_id": 26680,
      "paragraph_id": 0,
      "chapter": 180
    },
    {
      "line_id": "line_000072",
      "character_id": "char_narrator",
      "character_name": "Narrator",
      "text": "Alger leaned back , lifted his chin , and got carried away with his thoughts .",
      "emotion": "neutral",
      "start_token": 414338,
      "end_token": 414353,
      "sentence_id": 26681,
      "paragraph_id": 0,
      "chapter": 180
    },
    {
      "line_id": "line_000073",
      "character_id": "char_narrator",
      "character_name": "Narrator",
      "text": "Mr. Hanged Man ’s mental state does n’t seem to be normal ...",
      "emotion": "neutral",
      "start_token": 414354,
      "end_token": 414366,
      "sentence_id": 26682,
      "paragraph_id": 0,
      "chapter": 180
    },
    {
      "line_id": "line_000074",
      "character_id": "char_430",
      "character_name": "Audrey",
      "text": "Audrey looked at him with pity .",
      "emotion": "neutral",
      "start_token": 414367,
      "end_token": 414373,
      "sentence_id": 26683,
      "paragraph_id": 0,
      "chapter": 180
    },
    {
      "line_id": "line_000075",
      "character_id": "char_430",
      "character_name": "Audrey",
      "text": "She finally understood that there might be some sort of shocking secret behind the communication between Mr. Fool and The Sun , which led to The Hanged Man ’s loss of composure .",
      "emotion": "neutral",
      "start_token": 414374,
      "end_token": 414406,
      "sentence_id": 26684,
      "paragraph_id": 0,
      "chapter": 180
    },
    {
      "line_id": "line_000076",
      "character_id": "char_narrator",
      "character_name": "Narrator",
      "text": "After the Qilangos commission is over , I ’ll pay the price to get information about what Mr. Hanged Man learned today ...",
      "emotion": "neutral",
      "start_token": 414407,
      "end_token": 414429,
      "sentence_id": 26685,
      "paragraph_id": 0,
      "chapter": 180
    },
    {
      "line_id": "line_000077",
      "character_id": "char_narrator",
      "character_name": "Narrator",
      "text": "I wonder if he would be willing to ...",
      "emotion": "neutral",
      "start_token": 414430,
      "end_token": 414438,
      "sentence_id": 26686,
      "paragraph_id": 0,
      "chapter": 180
    },
    {
      "line_id": "line_000078",
      "character_id": "char_430",
      "character_name": "Audrey",
      "text": "Audrey thought in anticipation , yet was still a little worried .",
      "emotion": "neutral",
      "start_token": 414439,
      "end_token": 414450,
      "sentence_id": 26687,
      "paragraph_id": 0,
      "chapter": 180
    },
    {
      "line_id": "line_000079",
      "character_id": "char_762",
      "character_name": "Derrick",
      "text": "Derrick did n’t notice the weight that was hanging on his answer as he replied frankly , “ We build opulent altars covered in the Lord ’s symbol .",
      "emotion": "neutral",
      "start_token": 414451,
      "end_token": 414479,
      "sentence_id": 26688,
      "paragraph_id": 0,
      "chapter": 180
    },
    {
      "line_id": "line_000080",
      "character_id": "char_narrator",
      "character_name": "Narrator",
      "text": "Every time we receive a bumper Black - Faced Grass harvest , we hold a sacrificial ritual .",
      "emotion": "neutral",
      "start_token": 414480,
      "end_token": 414497,
      "sentence_id": 26689,
      "paragraph_id": 0,
      "chapter": 180
    },
    {
      "line_id": "line_000081",
      "character_id": "char_narrator",
      "character_name": "Narrator",
      "text": "“ We use the monsters we capture in the depths of the darkness to use as sacrificial offerings .",
      "emotion": "neutral",
      "start_token": 414498,
      "end_token": 414516,
      "sentence_id": 26690,
      "paragraph_id": 0,
      "chapter": 180
    },
    {
      "line_id": "line_000082",
      "character_id": "char_narrator",
      "character_name": "Narrator",
      "text": "After we recite God ’s honorable title and the necessary prayers , we dance for Him and then kill the monsters , to let their spirituality and tainted blood dye the entire altar .",
      "emotion": "neutral",
      "start_token": 414517,
      "end_token": 414550,
      "sentence_id": 26691,
      "paragraph_id": 0,
      "chapter": 180
    },
    {
      "line_id": "line_000083",
      "character_id": "char_narrator",
      "character_name": "Narrator",
      "text": "If we have n’t caught any monsters , then we use a sinner on the lowest floor in the City of Silver prison instead .",
      "emotion": "neutral",
      "start_token": 414551,
      "end_token": 414575,
      "sentence_id": 26692,
      "paragraph_id": 0,
      "chapter": 180
    },
    {
      "line_id": "line_000084",
      "character_id": "char_narrator",
      "character_name": "Narrator",
      "text": "“ Then , we turn the very first batch of Black - Faced Grass into food and serve it before the Lord .",
      "emotion": "neutral",
      "start_token": 414576,
      "end_token": 414598,
      "sentence_id": 26693,
      "paragraph_id": 0,
      "chapter": 180
    },
    {
      "line_id": "line_000085",
      "character_id": "char_narrator",
      "character_name": "Narrator",
      "text": "“ In the end , we sing praises in unison and end the ritual . ” Since I was planning to offer a sacrifice to myself , I ’m not picky about time , and the altar can be as simple as possible .",
      "emotion": "neutral",
      "start_token": 414599,
      "end_token": 414642,
      "sentence_id": 26694,
      "paragraph_id": 0,
      "chapter": 180
    },
    {
      "line_id": "line_000086",
      "character_id": "char_narrator",
      "character_name": "Narrator",
      "text": "The most important part would be to open a channel with the aid of the monsters ’ spirituality or the blood containing Beyonder powers to complete the sacrifice offering .",
      "emotion": "neutral",
      "start_token": 414643,
      "end_token": 414672,
      "sentence_id": 26695,
      "paragraph_id": 0,
      "chapter": 180
    },
    {
      "line_id": "line_000087",
      "character_id": "char_narrator",
      "character_name": "Narrator",
      "text": "Of course , this is under the premise that one will receive a response ?",
      "emotion": "neutral",
      "start_token": 414673,
      "end_token": 414687,
      "sentence_id": 26696,
      "paragraph_id": 0,
      "chapter": 180
    },
    {
      "line_id": "line_000088",
      "character_id": "char_narrator",
      "character_name": "Narrator",
      "text": "How extravagant ...",
      "emotion": "neutral",
      "start_token": 414688,
      "end_token": 414690,
      "sentence_id": 26697,
      "paragraph_id": 0,
      "chapter": 180
    },
    {
      "line_id": "line_000089",
      "character_id": "char_417",
      "character_name": "Klein",
      "text": "Klein used his mysticism knowledge to analyze every step of the sacrificial ritual in the City of Silver before finally saying , “ What are the corresponding prayers ?",
      "emotion": "neutral",
      "start_token": 414691,
      "end_token": 414719,
      "sentence_id": 26698,
      "paragraph_id": 0,
      "chapter": 180
    },
    {
      "line_id": "line_000090",
      "character_id": "char_narrator",
      "character_name": "Narrator",
      "text": "What language do you recite them in ? ”",
      "emotion": "neutral",
      "start_token": 414720,
      "end_token": 414728,
      "sentence_id": 26699,
      "paragraph_id": 0,
      "chapter": 180
    },
    {
      "line_id": "line_000091",
      "character_id": "char_762",
      "character_name": "Derrick",
      "text": "Derrick was also looking forward to this , so as to gain hints from Mr. Fool on how to shake off the curse , so he recalled it carefully and answered , “ We use Jotun , which is also our common language .",
      "emotion": "neutral",
      "start_token": 414729,
      "end_token": 414772,
      "sentence_id": 26700,
      "paragraph_id": 0,
      "chapter": 180
    },
    {
      "line_id": "line_000092",
      "character_id": "char_narrator",
      "character_name": "Narrator",
      "text": "“ The corresponding prayers are , “ ‘ Your devoted believers pray for your attention .",
      "emotion": "neutral",
      "start_token": 414773,
      "end_token": 414788,
      "sentence_id": 26701,
      "paragraph_id": 0,
      "chapter": 180
    },
    {
      "line_id": "line_000093",
      "character_id": "char_narrator",
      "character_name": "Narrator",
      "text": "“ We pray for you to take their offerings .",
      "emotion": "neutral",
      "start_token": 414789,
      "end_token": 414798,
      "sentence_id": 26702,
      "paragraph_id": 0,
      "chapter": 180
    },
    {
      "line_id": "line_000094",
      "character_id": "char_narrator",
      "character_name": "Narrator",
      "text": "“ We pray for you to open the gates to your Kingdom . ’ ” ...",
      "emotion": "neutral",
      "start_token": 414799,
      "end_token": 414814,
      "sentence_id": 26703,
      "paragraph_id": 0,
      "chapter": 180
    },
    {
      "line_id": "line_000095",
      "character_id": "char_417",
      "character_name": "Klein",
      "text": "Klein listened in silence and intentionally let the engulfing fog slowly swirl around him .",
      "emotion": "neutral",
      "start_token": 414815,
      "end_token": 414829,
      "sentence_id": 26704,
      "paragraph_id": 0,
      "chapter": 180
    },
    {
      "line_id": "line_000096",
      "character_id": "char_417",
      "character_name": "Klein",
      "text": "He nodded as though deep in thought and remained silent .",
      "emotion": "neutral",
      "start_token": 414830,
      "end_token": 414840,
      "sentence_id": 26705,
      "paragraph_id": 0,
      "chapter": 180
    },
    {
      "line_id": "line_000097",
      "character_id": "char_narrator",
      "character_name": "Narrator",
      "text": "As for what he learned from it , he obviously would n’t share it ...",
      "emotion": "neutral",
      "start_token": 414841,
      "end_token": 414855,
      "sentence_id": 26706,
      "paragraph_id": 0,
      "chapter": 180
    },
    {
      "line_id": "line_000098",
      "character_id": "char_narrator",
      "character_name": "Narrator",
      "text": "Alger found it very normal .",
      "emotion": "neutral",
      "start_token": 414856,
      "end_token": 414861,
      "sentence_id": 26707,
      "paragraph_id": 0,
      "chapter": 180
    },
    {
      "line_id": "line_000099",
      "character_id": "char_narrator",
      "character_name": "Narrator",
      "text": "How could the secrets of a deity be revealed directly to a mortal ?",
      "emotion": "neutral",
      "start_token": 414862,
      "end_token": 414875,
      "sentence_id": 26708,
      "paragraph_id": 0,
      "chapter": 180
    },
    {
      "line_id": "line_000100",
      "character_id": "char_762",
      "character_name": "Derrick",
      "text": "Derrick also steeled his resolve to quickly grow in power , so that he could obtain something that could garner Mr. Fool ’s interest in exchange for his guidance .",
      "emotion": "neutral",
      "start_token": 414876,
      "end_token": 414905,
      "sentence_id": 26709,
      "paragraph_id": 0,
      "chapter": 180
    },
    {
      "line_id": "line_000101",
      "character_id": "char_417",
      "character_name": "Klein",
      "text": "After some more communication , Klein ended the gathering .",
      "emotion": "neutral",
      "start_token": 414906,
      "end_token": 414915,
      "sentence_id": 26710,
      "paragraph_id": 0,
      "chapter": 180
    },
    {
      "line_id": "line_000102",
      "character_id": "char_417",
      "character_name": "Klein",
      "text": "He watched Justice ’s , The Hanged Man ’s , and The Sun ’s figures vanish before him .",
      "emotion": "neutral",
      "start_token": 414916,
      "end_token": 414934,
      "sentence_id": 26711,
      "paragraph_id": 0,
      "chapter": 180
    },
    {
      "line_id": "line_000103",
      "character_id": "char_417",
      "character_name": "Klein",
      "text": "He looked down and saw the boundless gray fog and crimson stars that seemed eternally immutable .",
      "emotion": "neutral",
      "start_token": 414935,
      "end_token": 414951,
      "sentence_id": 26712,
      "paragraph_id": 0,
      "chapter": 180
    },
    {
      "line_id": "line_000104",
      "character_id": "char_417",
      "character_name": "Klein",
      "text": "However , after he advanced to Sequence 8 , he realized that he could connect even more stars .",
      "emotion": "neutral",
      "start_token": 414952,
      "end_token": 414970,
      "sentence_id": 26713,
      "paragraph_id": 0,
      "chapter": 180
    },
    {
      "line_id": "line_000105",
      "character_id": "char_narrator",
      "character_name": "Narrator",
      "text": "In other words , he could pull in more members .",
      "emotion": "neutral",
      "start_token": 414971,
      "end_token": 414981,
      "sentence_id": 26714,
      "paragraph_id": 0,
      "chapter": 180
    },
    {
      "line_id": "line_000106",
      "character_id": "char_narrator",
      "character_name": "Narrator",
      "text": "At least two ...",
      "emotion": "neutral",
      "start_token": 414982,
      "end_token": 414985,
      "sentence_id": 26715,
      "paragraph_id": 0,
      "chapter": 180
    },
    {
      "line_id": "line_000107",
      "character_id": "char_417",
      "character_name": "Klein",
      "text": "Klein nodded indiscernibly .",
      "emotion": "neutral",
      "start_token": 414986,
      "end_token": 414989,
      "sentence_id": 26716,
      "paragraph_id": 0,
      "chapter": 180
    },
    {
      "line_id": "line_000108",
      "character_id": "char_417",
      "character_name": "Klein",
      "text": "He was n’t in a hurry to add new members .",
      "emotion": "neutral",
      "start_token": 414990,
      "end_token": 415000,
      "sentence_id": 26717,
      "paragraph_id": 0,
      "chapter": 180
    },
    {
      "line_id": "line_000109",
      "character_id": "char_417",
      "character_name": "Klein",
      "text": "He planned to act as he had before .",
      "emotion": "neutral",
      "start_token": 415001,
      "end_token": 415009,
      "sentence_id": 26718,
      "paragraph_id": 0,
      "chapter": 180
    },
    {
      "line_id": "line_000110",
      "character_id": "char_417",
      "character_name": "Klein",
      "text": "He would first wait and observe .",
      "emotion": "neutral",
      "start_token": 415010,
      "end_token": 415016,
      "sentence_id": 26719,
      "paragraph_id": 0,
      "chapter": 180
    },
    {
      "line_id": "line_000111",
      "character_id": "char_narrator",
      "character_name": "Narrator",
      "text": "If Justice and The Hanged Man had any recommendations , he could assess them first .",
      "emotion": "neutral",
      "start_token": 415017,
      "end_token": 415032,
      "sentence_id": 26720,
      "paragraph_id": 0,
      "chapter": 180
    },
    {
      "line_id": "line_000112",
      "character_id": "char_narrator",
      "character_name": "Narrator",
      "text": "What I saw the last few times was when The Sun was praying .",
      "emotion": "neutral",
      "start_token": 415033,
      "end_token": 415046,
      "sentence_id": 26721,
      "paragraph_id": 0,
      "chapter": 180
    },
    {
      "line_id": "line_000113",
      "character_id": "char_narrator",
      "character_name": "Narrator",
      "text": "There was a clear crystal ball before him , but ever since I pulled him into the world above the gray fog , that crystal ball has never appeared again ...",
      "emotion": "neutral",
      "start_token": 415047,
      "end_token": 415077,
      "sentence_id": 26722,
      "paragraph_id": 0,
      "chapter": 180
    },
    {
      "line_id": "line_000114",
      "character_id": "char_narrator",
      "character_name": "Narrator",
      "text": "Does the prerequisite needed to pull people in through the connection of the crimson star have something to do with having a special item around them ?",
      "emotion": "neutral",
      "start_token": 415078,
      "end_token": 415104,
      "sentence_id": 26723,
      "paragraph_id": 0,
      "chapter": 180
    },
    {
      "line_id": "line_000115",
      "character_id": "char_narrator",
      "character_name": "Narrator",
      "text": "Or does every crimson star correspond to an item in reality , which , when it ’s connected successfully , it would return to the world above the gray fog ?",
      "emotion": "neutral",
      "start_token": 415105,
      "end_token": 415135,
      "sentence_id": 26724,
      "paragraph_id": 0,
      "chapter": 180
    },
    {
      "line_id": "line_000116",
      "character_id": "char_000",
      "character_name": "Character_10000",
      "text": "I wonder if Miss Justice and Mr. Hanged Man were the same ...",
      "emotion": "neutral",
      "start_token": 415136,
      "end_token": 415148,
      "sentence_id": 26725,
      "paragraph_id": 0,
      "chapter": 180
    },
    {
      "line_id": "line_000117",
      "character_id": "char_narrator",
      "character_name": "Narrator",
      "text": "Let ’s just assume that ’s the case .",
      "emotion": "neutral",
      "start_token": 415149,
      "end_token": 415157,
      "sentence_id": 26726,
      "paragraph_id": 0,
      "chapter": 180
    },
    {
      "line_id": "line_000118",
      "character_id": "char_narrator",
      "character_name": "Narrator",
      "text": "In that case , if people without this special item were to recite : “ The Fool that does n’t belong to this era , the mysterious ruler above the gray fog ; the King of Yellow and Black who wields good luck . ”",
      "emotion": "neutral",
      "start_token": 415158,
      "end_token": 415202,
      "sentence_id": 26727,
      "paragraph_id": 0,
      "chapter": 180
    },
    {
      "line_id": "line_000119",
      "character_id": "char_narrator",
      "character_name": "Narrator",
      "text": "and allow me to hear their prayers , would I be able to pull them in ? I can give it a try in the future .",
      "emotion": "neutral",
      "start_token": 415203,
      "end_token": 415229,
      "sentence_id": 26728,
      "paragraph_id": 0,
      "chapter": 180
    },
    {
      "line_id": "line_000120",
      "character_id": "char_417",
      "character_name": "Klein",
      "text": "Klein did n’t stay any longer .",
      "emotion": "neutral",
      "start_token": 415230,
      "end_token": 415236,
      "sentence_id": 26729,
      "paragraph_id": 0,
      "chapter": 180
    },
    {
      "line_id": "line_000121",
      "character_id": "char_417",
      "character_name": "Klein",
      "text": "He wrapped himself with spirituality and stimulated a descent , leaving behind the lofty palace , the ancient table , and the twenty - two high - back chairs which sat immutably above the gray fog .",
      "emotion": "neutral",
      "start_token": 415237,
      "end_token": 415273,
      "sentence_id": 26730,
      "paragraph_id": 0,
      "chapter": 180
    },
    {
      "line_id": "line_000122",
      "character_id": "char_417",
      "character_name": "Klein",
      "text": "He had mastered the overflowing power of the Clown potion and eliminated the corresponding negative effects .",
      "emotion": "neutral",
      "start_token": 415274,
      "end_token": 415290,
      "sentence_id": 26731,
      "paragraph_id": 0,
      "chapter": 180
    },
    {
      "line_id": "line_000123",
      "character_id": "char_narrator",
      "character_name": "Narrator",
      "text": "Therefore , he wanted to try the ritual to summon himself !",
      "emotion": "neutral",
      "start_token": 415291,
      "end_token": 415302,
      "sentence_id": 26732,
      "paragraph_id": 0,
      "chapter": 180
    },
    {
      "line_id": "line_000124",
      "character_id": "char_000",
      "character_name": "Character_10000",
      "text": "I wonder what I ’ll conjure this time ...",
      "emotion": "neutral",
      "start_token": 415303,
      "end_token": 415311,
      "sentence_id": 26733,
      "paragraph_id": 0,
      "chapter": 180
    },
    {
      "line_id": "line_000125",
      "character_id": "char_417",
      "character_name": "Klein",
      "text": "Klein thought in anticipation and fear as he fell through the mad ravings .",
      "emotion": "anger",
      "start_token": 415312,
      "end_token": 415325,
      "sentence_id": 26734,
      "paragraph_id": 0,
      "chapter": 180
    }
  ]
}